{"selv\u00e4ksi": 1, "kolmannes": 1, "teht\u00e4vi\u00e4": 10, "kieleksi": 3, "nelj\u00e4s": 1, "esiintyv\u00e4n": 2, "arvioida": 1, "harjoitella": 2, "kuviokielen": 1, "kannustuksesta": 1, "k\u00e4\u00e4nn\u00f6svirhe": 1, "mielenkiintoinen": 1, "kuvata": 1, "ty\u00f6el\u00e4m\u00e4ss\u00e4": 1, "kommentteja": 2, "tietyist\u00e4": 1, "ym": 15, "development": 1, "changing": 1, "linjassa": 1, "yht\u00e4": 3, "suinkaan": 2, "opetustilanteessa": 2, "hetkell\u00e4": 1, "sen": 33, "liikkuminen": 1, "kirjoitettu": 4, "yksil\u00f6t": 1, "olleisiin": 1, "vaihetta": 1, "kumpuaa": 1, "viitata": 1, "understanding": 1, "esimerkkiarviointeja": 1, "hyvin": 22, "rooli": 2, "per\u00e4ss\u00e4": 1, "merkityksi\u00e4": 2, "l\u00e4hes": 4, "konkreettisesta": 1, "monta": 1, "v\u00e4lisen": 2, "tarkistaa": 1, "1991": 2, "jaetaan": 2, "with": 1, "p\u00e4\u00e4st\u00e4\u00e4n": 1, "sanallisten": 4, "tapaan": 1, "ilmaukset": 1, "hiebert": 5, "alussa": 2, "tarkoittaa": 4, "acta": 1, "osiossa": 1, "puolet": 4, "korvattua": 1, "esityksen": 1, "enk\u00e4": 1, "opintoja": 3, "entendre": 1, "opettaja": 7, "asialla": 1, "kannalta": 1, "opiskelijat": 24, "mahdollinen": 2, "laskutoimitussymboleilla": 1, "tiedot": 3, "virheit\u00e4": 6, "pysty\u00e4": 1, "osoittaa": 2, "toteutus": 3, "eteen": 1, "ratkaisuihin": 1, "vastaamiseen": 1, "liittyv\u00e4": 2, "ker\u00e4ystapaa": 1, "etenee": 1, "oppimisessa": 1, "mallina": 1, "tuonut": 1, "vrt": 3, "kis\u00e4lliopetusta": 1, "teht\u00e4v\u00e4tyypeist\u00e4": 1, "my\u00f6hempi\u00e4": 1, "muotoilemaan": 1, "raportteja": 1, "olisi": 17, "positiivisten": 1, "pitk\u00e4lti": 2, "enimm\u00e4kseen": 1, "nimityst\u00e4": 1, "voitu": 2, "pyrittiin": 6, "toiseksi": 1, "adu-gyamfin": 1, "vaikeinta": 2, "tarvitaankin": 1, "pisteytetty": 2, "laskennassa": 2, "sis\u00e4lt\u00f6\u00f6n": 1, "kyseisen": 1, "kahdesta": 2, "mitattiin": 1, "merkinn\u00f6in": 1, "pikakirjoitusmaista": 1, "motivoivuutta": 1, "standardi": 1, "kirjoittamalla": 2, "kiivet\u00e4": 1, "vaille": 1, "heill\u00e4": 1, "leikkauksen": 1, "kirjoittaa": 13, "lukiolaisen": 1, "teht\u00e4v\u00e4\u00e4ratkaisua": 1, "ymm\u00e4rt\u00e4m\u00e4\u00e4n": 3, "muodostuu": 4, "helpottavana": 1, "06\u2264|\ud835\udc5f|08": 1, "tuntuneet": 1, "aloin": 1, "selitt\u00e4minenperusteleminen": 1, "kieleen": 5, "ovatko": 2, "tavat": 1, "harmaalla": 3, "tutkittava": 1, "luonteeseen": 1, "kohdissa": 2, "kohtaamia": 1, "laskuharjoitusten": 2, "moni": 5, "31\u201383": 1, "kriteerien": 3, "arkikieless\u00e4": 3, "kielent\u00e4misteht\u00e4viin": 2, "educational": 1, "samaakin": 1, "aikaa": 5, "cognitive": 2, "korkea": 3, "ongelmaksi": 1, "koodin": 1, "algebrallista": 1, "matematiikaksi": 1, "congress": 1, "\ud835\udc65\u2208\ud835\udc35": 1, "nikula": 2, "learning": 9, "k\u00e4\u00e4nt\u00e4\u00e4": 2, "kiitos": 1, "ratkaisen": 2, "42004": 1, "reflektoiva": 1, "korvattu": 1, "sis\u00e4lle": 5, "muiden": 3, "l\u00e4hteet": 2, "erillisten": 1, "maailman": 1, "sanalliset": 2, "hyvinkin": 3, "tyyppisell\u00e4": 1, "kie": 2, "mielell\u00e4\u00e4n": 1, "syv\u00e4llisesti": 1, "esiinty\u00e4": 1, "t\u00e4ytyy": 2, "symboleita": 3, "opintopiireilij\u00f6ille": 1, "1996": 17, "ajallisesti": 1, "sovelletaan": 1, "painotusten": 1, "sanallisesti": 13, "r056": 1, "l\u00e4ht\u00f6kohdiksi": 1, "analysointimenetelmi\u00e4": 1, "vastauksensa": 1, "oikeastaan": 2, "tapaa": 4, "auki": 1, "joukko-opillisen": 1, "tyyli\u00e4": 1, "matemaattisesti": 4, "vertailtaessa": 1, "osat": 1, "mekaanisen": 1, "maailma": 4, "keskeist\u00e4": 1, "k\u00e4ytt\u00e4en": 3, "vastauksesta": 3, "esitettyyn": 1, "joissakin": 1, "erilaisista": 1, "teetetyt": 1, "tukitoimilla": 1, "oikeustieteest\u00e4": 1, "ovia": 1, "matematiikkak\u00e4sitysten": 1, "jokin": 2, "miinusmerkkinen": 1, "tietojen": 3, "pohtineet": 1, "suullisesti": 4, "kysymyksell\u00e4": 1, "sellaisenaan": 1, "ajatuksiaan": 1, "erottelevampia": 1, "havainnoidessaan": 1, "avoimiin": 2, "peruskoulussa": 1, "perceived": 1, "symboli": 2, "yliopistotason": 1, "teht\u00e4v\u00e4t": 5, "huomannut": 2, "sis\u00e4lt\u00f6\u00e4": 4, "olen": 4, "erilaisia": 3, "yksitt\u00e4istapauksia": 1, "r062": 2, "yhteyksien": 1, "48\u201351": 1, "helpompi": 4, "ratkaisuani": 2, "k\u00e4sitteen\u00e4": 1, "piti": 3, "l\u00e4hestynyt": 1, "sis\u00e4lsi": 1, "vaikeampaa": 2, "hy\u00f6dynnettiin": 1, "puoliskon": 1, "ajattelussaan": 1, "t\u00e4sm\u00e4llisyyteen": 1, "kuvassa": 10, "varsin": 4, "ratkaisuni": 2, "formaalin": 1, "kuulin": 1, "turhaan": 2, "hyv\u00e4": 1, "j\u00e4": 1, "lapin": 2, "ymm\u00e4rrett\u00e4v\u00e4n": 1, "heikent\u00e4\u00e4": 1, "teht\u00e4v\u00e4n": 55, "matematiikkaa": 12, "t\u00e4sm\u00e4llisyys": 1, "ilmaisutapoja": 1, "sanavalinnoilla": 1, "ty\u00f6ss\u00e4ni": 1, "palauttaneet": 1, "ensimm\u00e4isen": 5, "menetelm\u00e4\u00e4": 2, "kielill\u00e4": 1, "tall": 6, "todistuksen": 11, "theology": 1, "toistettavuutta": 4, "havaittuja": 1, "merkin": 5, "tutkimusta": 3, "v\u00e4h\u00e4isempi": 1, "l\u00e4pin\u00e4kyvyyden": 1, "opettajan": 5, "kyselyyn": 3, "turhautumiseen": 1, "tasolle": 1, "k\u00e4ytt\u00f6tilanteesta": 1, "kehitt\u00e4m\u00e4\u00e4n": 1, "symbolikielell\u00e4": 6, "ongelmat": 2, "muille": 11, "yhteyden": 1, "edist\u00e4v\u00e4t": 1, "olevan": 8, "k\u00e4yneelle": 1, "osaamiskokemusta": 1, "potentiaalisia": 1, "nelj\u00e4nnest\u00e4": 2, "selke\u00e4": 1, "harjulehto": 1, "nimityksist\u00e4": 1, "havaitut": 1, "t\u00e4rke\u00e4\u00e4": 5, "johtavaa": 1, "mill\u00e4": 4, "uutta": 1, "l\u00e4hestymistapa": 1, "oppikirjoissa": 2, "suhteet": 1, "rakentuu": 1, "olioista": 1, "nimityksi\u00e4": 5, "m\u00e4\u00e4ritelmi\u00e4": 1, "korrelaatiokerrointa": 1, "ajatteluprosessin": 2, "suhteessa": 1, "niist\u00e4": 6, "viestim\u00e4\u00e4n": 2, "painottaa": 2, "kielent\u00e4misn\u00e4k\u00f6kulmasta": 2, "lukuihin": 1, "uuden": 1, "single": 1, "oletusta": 1, "ajattelemaan": 1, "tapa": 3, "perinteist\u00e4": 3, "verrattuna": 5, "verkkojulkaisu": 1, "takaisi": 1, "kriteereill\u00e4": 2, "kaikkea": 2, "vaikea": 1, "akohdassa": 1, "ohjaavat": 1, "rekisterieroista": 1, "luoda": 1, "vastaamaan": 5, "siihen": 12, "9\u201331": 1, "konseptuaalista": 2, "yksi\u00f6": 1, "laajentaminen": 1, "opiskelijalaitos": 1, "oteta": 1, "semiotic": 1, "117\u2013118": 1, "abstraktin": 1, "esiintyy": 2, "k\u00e4ytt\u00e4ess\u00e4\u00e4n": 1, "julkaisuja": 2, "asiaa": 3, "selv\u00e4": 2, "kielent\u00e4v\u00e4\u00e4": 1, "pit\u00e4\u00e4": 7, "n\u00e4ist\u00e4kin": 1, "mielenkiintoista": 2, "molempiin": 3, "v\u00e4likokeeseen": 2, "operaatioille": 1, "vakiintunut": 1, "koepisteit\u00e4": 2, "hissin": 1, "kirjoittaminen": 8, "matematiikkakuva": 2, "soveltuvat": 1, "mathematically": 1, "koodinvaihtoteht\u00e4vist\u00e4": 1, "jokainen": 1, "mainita": 1, "where": 1, "varsinaiseksi": 1, "ajatteluaan": 7, "yht\u00e4suuruusmerkin": 1, "wagner": 2, "joukkojen": 3, "kehitt\u00e4minen": 4, "helpottuu": 1, "matemaattinen": 8, "ratkaisuksi": 1, "siirryt\u00e4\u00e4n": 1, "kielent\u00e4misharjoitukset": 1, "joensuu": 2, "perustelut": 2, "osiot": 1, "stereotypiat": 1, "oikeampi": 1, "muita": 5, "oppilaideni": 1, "puolustavat": 1, "ratkaisijan": 2, "t\u00e4sm\u00e4llinen": 1, "leikataan": 1, "katsetta": 1, "on": 218, "algoritmimaisesti": 1, "joita": 8, "tuttuja": 1, "lukio": 1, "language": 9, "taidon": 1, "pimm": 2, "analysointity\u00f6kaluja": 1, "osa-alueet": 1, "termit": 1, "l\u00e4hestymistapana": 1, "silti": 2, "aiheuttaisi": 1, "tyyliseksi": 1, "v\u00e4is\u00e4sen": 1, "todettiin": 2, "n\u00e4hd\u00e4": 2, "ominaisuuksia": 2, "kolmannen": 4, "esille": 1, "todistus": 2, "koodinvaihtotyyppiset": 1, "loogista": 1, "arkikielen": 1, "saavansa": 1, "koulumatematiikassa": 2, "haswell": 4, "kiinnitettiin": 2, "aihealueet": 1, "seikkana": 1, "n44": 1, "kokeesta": 1, "jaksaisi": 1, "viiden": 1, "t\u00e4rke\u00e4n\u00e4": 1, "kulttuurista": 1, "k\u00e4ytett\u00e4v\u00e4": 1, "muulla": 2, "v\u00e4itt\u00e4m\u00e4\u00e4": 1, "saatuja": 3, "siksi": 2, "luonnosteltiin": 1, "laskurutiinin": 3, "kognitiivisia": 1, "voitaisiin": 2, "k\u00e4sitekarttoja": 1, "232\u2013244": 1, "etenev\u00e4\u00e4": 1, "mm": 5, "kurssiarvosanaan": 2, "opettajankoulutuslaitos": 2, "reaalimaailmassa": 1, "l\u00f6yt\u00e4\u00e4": 4, "mahdollisuus": 3, "perusmalliin": 1, "muussa": 1, "riitt\u00e4\u00e4": 1, "yksitt\u00e4isi\u00e4": 1, "osaajana": 2, "syin\u00e4": 1, "ilmeisesti": 2, "nopeuttaa": 1, "tulevaisuutta": 1, "kaiken": 1, "suhtautuva": 1, "lepp\u00e4aho": 3, "soveltuu": 1, "tuottaminen": 4, "kommentoinut": 1, "muuttumiseen": 1, "auttaa": 6, "induktiotodistuksen": 1, "matemaattisia": 3, "t\u00e4m\u00e4ntyyppinen": 1, "olevasta": 1, "perusajatuksen": 1, "v\u00e4itt\u00e4m\u00e4": 2, "art": 1, "henkil\u00f6": 2, "aistein": 1, "menetelm\u00e4ss\u00e4": 1, "hankalammaksi": 1, "sis\u00e4ltyiv\u00e4t": 1, "kuviot": 2, "sanallisen": 6, "selitt\u00e4misen": 1, "haastavia": 1, "kursseilla": 3, "teknillisiss\u00e4": 1, "siten": 6, "finland": 1, "puuttui": 1, "k\u00e4sitteist\u00e4": 1, "itselleen": 7, "tiimity\u00f6skentelyyn": 1, "ihmisist\u00e4": 1, "ep\u00e4intuitiivisesti": 1, "erityispiirteet": 1, "rovaniemi": 1, "2016": 2, "koko": 5, "sanoja": 8, "kyll\u00e4": 2, "k\u00e4sitteellisess\u00e4": 1, "pelkoihin": 1, "kaksoismerkitys": 1, "v\u00e4hent\u00e4m\u00e4ll\u00e4": 1, "prosentilla": 2, "koostuuhan": 1, "selitt\u00e4misest\u00e4": 2, "kielist\u00e4": 1, "johtop\u00e4\u00e4t\u00f6ksen": 7, "kehityksess\u00e4": 1, "monipuolisesti": 1, "k\u00e4sitteleviss\u00e4": 1, "koulumatematiikan": 2, "t\u00e4h\u00e4n": 5, "milloinkin": 1, "matemaattis-luonnontieteellinen": 3, "prosessi": 2, "jorma": 1, "tyt\u00f6t": 1, "universitatis": 1, "ilmaisupisteet": 4, "nelj\u00e4ll\u00e4": 4, "elementit": 1, "pupil": 1, "yhdiste": 4, "ep\u00e4varmaa": 1, "monitieteisyytt\u00e4": 1, "microsoft": 1, "paljonkin": 2, "tamperensis": 1, "v\u00e4ite": 4, "kasvatustieteellisi\u00e4": 1, "k\u00e4ytt\u00e4m\u00e4ll\u00e4": 3, "oloni": 1, "kest\u00e4v\u00e4": 1, "tehty": 2, "m\u00e4\u00e4ritell\u00e4": 1, "osaamiskokemuksesta": 1, "jotkin": 1, "saatu": 2, "viisi": 2, "perinteisesti": 1, "omaksua": 1, "avainsanat": 1, "syksyll\u00e4": 1, "tarvitaan": 2, "m\u00e4cklin": 2, "muista": 1, "oppilailla": 2, "kirjaimesta": 1, "reston": 1, "kehitt\u00e4misess\u00e4": 1, "huom": 1, "virhealttiiksi": 1, "t\u00e4llaisessa": 2, "v\u00e4livaiheiden": 1, "aiheuttivat": 2, "erillist\u00e4": 1, "liittyv\u00e4n": 1, "todistusten": 1, "opetusviikon": 1, "negatiivisuudesta": 1, "lopuksi": 3, "is": 2, "ristiriita": 1, "kehittymist\u00e4": 1, "k\u00e4sityksen": 2, "p\u00e4\u00e4aine": 1, "kurssitunnustaan": 1, "kummastakin": 1, "tutkija": 1, "erilleen": 1, "p\u00e4\u00e4aineopiskelijoita": 3, "kurssimenestykseen": 4, "_____________________": 1, "seuraavissa": 1, "tehokas": 1, "laajempiin": 1, "tapahtuvaa": 1, "kurssilla": 11, "yhdess\u00e4": 3, "vastauksista": 6, "v\u00e4hint\u00e4\u00e4n": 8, "elementist\u00e4": 1, "yhteiset": 1, "johtuen": 2, "millainen": 1, "suoritetaan": 1, "jokaisen": 3, "lis\u00e4ksi": 25, "osa-alueeksi": 1, "opiskelussa": 2, "luonteva": 1, "interpretation": 1, "kirjoittamisessa": 1, "poikkeavan": 1, "wagnerin": 1, "xn": 1, "ilmaisu": 1, "mainitsee": 3, "kurssipisteiden": 1, "tai-sanaan": 1, "nimill\u00e4": 1, "hankalista": 1, "palautettiin": 4, "lawrence": 1, "osaajien": 1, "sopisivat": 1, "virheet": 2, "derivaatan": 1, "luonnolliselta": 1, "t\u00e4llaisesta": 2, "tuntevat": 1, "hallittiin": 1, "p\u00e4\u00e4siv\u00e4t": 1, "ep\u00e4illen": 1, "kenney": 1, "merkit": 1, "silt\u00e4": 1, "p\u00e4ihin": 1, "intuitioon": 1, "tavoitteet": 3, "kirjoittaja": 1, "vastaajat": 16, "pylv\u00e4skaaviosta": 1, "teht\u00e4v\u00e4tyypist\u00e4": 2, "monimutkaisempi": 2, "yksi": 3, "ehdon": 1, "puutteet": 1, "arvioijan": 2, "joutsenlahden": 11, "oikeuttavan": 1, "formaaliutta": 1, "tuota": 1, "yhdisteen": 7, "seuraamaan": 1, "thinking": 4, "osalta": 2, "viime": 2, "1000": 1, "itsens\u00e4": 1, "ratkaisemiseen": 3, "kiinnostunut": 1, "filosofiaan": 1, "ongelmasta": 1, "sarakkeeseen": 2, "harjoitusteht\u00e4v\u00e4\u00e4n": 1, "k\u00e4sinkirjoitettujen": 1, "tai": 66, "todistusteht\u00e4vi\u00e4": 1, "muuttuvat": 1, "luonne": 1, "tutkimuksesta": 1, "vaadittava": 1, "tutuksi": 1, "keskiarvo": 5, "b-kohtana": 1, "tutustutaan": 1, "esitt\u00e4mist\u00e4": 3, "koettiin": 2, "re": 1, "kupari": 1, "toistuvasti": 1, "todenn\u00e4k\u00f6isyyden": 1, "arvioidaan": 2, "antaa": 4, "v\u00e4hennykset": 1, "samanlaiset": 1, "toiselta": 1, "turun": 3, "lyhyt": 1, "huomata": 1, "valmiita": 1, "apua": 5, "olin": 1, "pages": 1, "algoritmeja": 1, "kiinni": 1, "kursseja": 2, "hallitaan": 1, "poistettu": 8, "rajoja": 1, "peruskoulun": 2, "joukot": 1, "jonka": 5, "do": 1, "toiminta": 1, "j\u00e4tti": 2, "yleens\u00e4": 3, "reflektoitua": 1, "kiinnitet\u00e4\u00e4n": 1, "kielent\u00e4misteht\u00e4v\u00e4\u00e4n": 2, "m\u00e4\u00e4ritell\u00e4\u00e4n": 1, "aihetta": 2, "proceptual-symbolic": 1, "liittyy": 2, "tehty\u00e4\u00e4n": 1, "taidot": 3, "strategioiden": 1, "tehostettua": 1, "ep\u00e4formaalista": 1, "l\u00e4hestytt\u00e4v\u00e4\u00e4": 1, "verrata": 1, "pyyt\u00e4\u00e4": 1, "yrit\u00e4": 1, "toivat": 1, "osannut": 1, "opiskelijoille": 12, "l\u00e4hesty\u00e4": 1, "kuvat": 1, "integraalin": 2, "viitekehyst\u00e4": 1, "uudistettu": 1, "tunnisti": 1, "sis\u00e4lt\u00e4m\u00e4n": 2, "vastineet": 1, "a-kohdan": 1, "erityisen": 3, "keskiarvon": 1, "v\u00e4likokeista": 1, "tavoitteena": 6, "kehitt\u00e4miseen": 2, "visuospatiaalisesti": 1, "kirjallisesti": 3, "joukkoa": 1, "henkil\u00f6iden": 1, "lis\u00e4valoa": 1, "ominaisuuksien": 1, "m\u00e4\u00e4rittelem\u00e4tt\u00e4": 1, "ulkopuolisia": 1, "uudestaan": 1, "se": 26, "kaikista": 5, "vatko": 1, "cas-laskinten": 1, "kielent\u00e4misteht\u00e4vist\u00e4": 6, "merkitykset": 1, "my\u00f6s": 82, "neliportaisella": 1, "muuttujan": 1, "helpompaa": 4, "symbolien": 9, "f\u00f6rvaringsst\u00e4lle": 1, "t\u00e4llaista": 1, "j\u00e4sent\u00e4miskeinoksi": 1, "saatavien": 1, "nostaa": 1, "selvitt\u00e4m\u00e4\u00e4n": 4, "niit\u00e4": 15, "ratkaisut": 2, "32(6": 1, "muun": 1, "vaaditaan": 1, "vastausesimerkiss\u00e4": 1, "erinomaisesti": 1, "ongelmaa": 1, "osaltaan": 4, "sanallista": 5, "osallistu": 1, "oppiminen": 3, "lukioissa": 1, "oinoselle": 1, "j\u00e4sent\u00e4m\u00e4\u00e4n": 2, "k\u00e4sitell\u00e4\u00e4n": 11, "puolelle": 1, "formalisation": 1, "kokemusten": 1, "esimerkiksi": 39, "osaamiskokemustaan": 1, "t\u00e4sm\u00e4llisyydest\u00e4": 1, "pakottavan": 1, "l\u00e4hteist\u00e4": 1, "leikkausta": 1, "puusniekka": 3, "ajattelua": 5, "uudenlainen": 1, "integraali": 1, "silfverberg": 1, "diplomity\u00f6": 2, "luonnollisen": 17, "yksil\u00f6ity\u00e4": 1, "etsim\u00e4\u00e4n": 1, "pistem\u00e4\u00e4r\u00e4": 2, "palauttanut": 1, "valmiista": 1, "kirjojen": 1, "jossa": 15, "lause": 1, "david": 1, "tunnustaan": 1, "joko": 7, "tulkinta-asteikko": 1, "ennusta": 1, "hy\u00f6ty": 2, "suunnattuun": 1, "tuleviin": 1, "savolainen": 1, "tutkimustuloksia": 1, "pyyt\u00e4m\u00e4ll\u00e4": 1, "siirtym\u00e4n\u00e4": 1, "positiivisuudesta": 1, "mink\u00e4": 5, "kutsutun": 1, "kannattaisiko": 1, "yht\u00e4l\u00f6t": 3, "tunne": 2, "haluan": 2, "ratkaisuprosessin": 1, "msk": 1, "mi": 1, "tarvittavaa": 1, "esitykseen": 1, "erityist\u00e4": 1, "kertaa": 2, "mlk": 1, "vaivaa": 1, "tarpeen": 2, "k\u00e4sinkirjoitettua": 1, "poiketen": 1, "tarkastellessani": 1, "christiansen": 3, "n\u00e4htiin": 1, "kuulee": 1, "esiintyv\u00e4": 2, "valmis": 2, "terveisin": 1, "sanallinen": 4, "selit\u00e4n": 2, "kuvaillaan": 1, "enemm\u00e4n": 8, "kullekin": 1, "vaihtelua": 3, "1978": 2, "gradua": 1, "yksitt\u00e4isen": 3, "virheen": 4, "referat": 1, "yhden": 9, "kauttaaltaan": 1, "tukeminen": 1, "menetelm\u00e4tieto": 1, "\ud835\udc4e\u2208\ud835\udc35": 1, "riippuvuutta": 3, "korkeintaan": 3, "k\u00e4ytt\u00f6kelpoiselta": 2, "kohdan": 1, "perusteellisuuden": 2, "joutsenlahti": 41, "varsinaista": 1, "ymp\u00e4r\u00f6iv\u00e4n": 1, "saamien": 2, "hahmottaa": 5, "loppuarvosana": 1, "2\u20135": 1, "luokittelusta": 1, "jakaa": 4, "kielteiseen": 1, "toisinaan": 4, "kielent\u00e4mismalleja": 1, "auttoivat": 1, "0\u20132": 1, "tensions": 1, "aineistoa": 5, "yhteys": 8, "saamaa": 2, "siirtymist\u00e4": 1, "teht\u00e4v\u00e4nannon": 7, "syyt\u00e4": 3, "j\u00e4lkik\u00e4teen": 1, "kaavan": 1, "todenn\u00e4k\u00f6isesti": 1, "perinteisest\u00e4": 1, "tutkit-tiin": 1, "notkahdus": 1, "vastasi": 2, "t\u00e4st\u00e4": 9, "muotoilu": 1, "suotavaa": 1, "ainakaan": 1, "puhtaasti": 2, "experiencing": 1, "tutkimuksessa": 18, "auttavat": 1, "muotoili": 1, "itsess\u00e4\u00e4n": 3, "liitteest\u00e4": 1, "k\u00e4ytetty\u00e4": 1, "issues": 2, "morgan": 4, "hy\u00f6dylliseksi": 4, "osittain": 6, "joka": 17, "itse": 11, "parempaa": 1, "v\u00e4hennystenk\u00e4\u00e4n": 1, "ymm\u00e4rt\u00e4minen": 3, "sellaisista": 1, "joillekin": 1, "ty\u00f6j\u00e4rjestyksen": 1, "keskustelitko": 1, "tekemiseen": 1, "overcoming": 1, "yhdell\u00e4": 1, "pyrki\u00e4": 2, "tarkastelun": 2, "12th": 1, "kieli": 12, "rakenteista": 1, "elliott": 1, "asikainen": 1, "keskialueen": 1, "vastaajan": 5, "entist\u00e4": 1, "231\u2013243": 1, "jokaiselle": 2, "ratkoa": 2, "enthusiast": 1, "k\u00e4ytt\u00f6kelpoista": 1, "auttoi": 1, "mathematics": 27, "lukum\u00e4\u00e4r\u00e4\u00e4": 1, "1993": 2, "ymm\u00e4rryst\u00e4": 1, "maksimim\u00e4\u00e4r\u00e4n": 1, "kegan": 1, "rakenteita": 2, "havainnollistavaa": 1, "erilaiset": 1, "lukukauden": 1, "tulkita": 2, "osallistui": 2, "alakerran": 1, "aineistoani": 1, "yliopisto-opetus": 1, "valmiiksi": 2, "tekeminen": 4, "tiettyj\u00e4": 1, "kysymysten": 1, "ratkaisuista": 1, "prosenttiosuus": 6, "ohjenuoranani": 1, "department": 1, "jota": 3, "k\u00e4ytt\u00e4m\u00e4ns\u00e4": 7, "keskittynyt": 1, "suoriutuivat": 1, "nj": 1, "asioihin": 1, "ratkaisemista": 1, "j\u00e4\u00e4d\u00e4": 3, "kohtaa": 2, "kolmessa": 1, "jos": 15, "ilmausten": 1, "arvioijaa": 1, "tasaisesti": 1, "virhe": 1, "k-12": 1, "toteutettua": 1, "hyv\u00e4st\u00e4": 1, "toiminnasta": 1, "puoliv\u00e4liin": 1, "ihmistieteiss\u00e4": 1, "hy\u00f6dynt\u00e4m\u00e4ll\u00e4": 1, "joukko-opin": 13, "ehk\u00e4": 4, "seuraavasti": 3, "pient\u00e4": 1, "teht\u00e4v\u00e4nannossa": 1, "tehneille": 1, "etsimist\u00e4": 1, "analysoitu": 1, "t\u00f6rm\u00e4\u00e4kin": 1, "saati": 1, "todellisuutta": 1, "oikeellisuuteen": 1, "reilu": 2, "hy\u00f6dyt": 3, "tarjoaa": 1, "hyv\u00e4ksyt\u00e4\u00e4n": 1, "v\u00e4\u00e4r\u00e4": 1, "kaavamaisesti": 1, "houkuttelevampi": 1, "teht\u00e4v\u00e4\u00e4": 11, "keskialueeseen": 1, "jamisonin": 4, "samassa": 2, "puhuttaessa": 4, "itselle": 1, "joutsenlahtikin": 1, "saamiin": 1, "kielent\u00e4misharjoittelun": 3, "tehdyss\u00e4": 2, "n\u00e4ytt\u00e4\u00e4": 2, "v\u00e4\u00e4r\u00e4ll\u00e4": 1, "tarvittavan": 1, "mahdollisuuden": 1, "jutteli": 2, "kriittisi\u00e4": 1, "59\u201370": 1, "pohtiikin": 1, "vastaaja": 37, "erilainen": 1, "heikentyneen": 1, "jollakulla": 1, "hy\u00f6dyllisiksi": 2, "p-arvojen": 1, "matematiikan": 172, "yhteydest\u00e4": 1, "kieliopillisia": 1, "harjoituksia": 1, "valtaosa": 5, "jolloin": 9, "annual": 1, "itsen\u00e4isesti": 2, "classroom": 2, "k\u00e4sittelev\u00e4tk\u00f6": 1, "sujuvasti": 2, "tiettyjen": 1, "toteutettiin": 5, "osmoottisesti": 1, "toista": 2, "joukossa": 2, "vuoksi": 2, "tarkastelemalla": 1, "k\u00e4ytetyt": 1, "katsoo": 1, "uudistetaan": 1, "arviointikriteerien": 2, "suomenkielisess\u00e4": 1, "k\u00e4ytt\u00e4isiv\u00e4tk\u00f6": 1, "tunsivat": 1, "pisteskaalan": 1, "1\u20261": 1, "luontainen": 1, "ihmiset": 1, "huomautuksen": 2, "seuraaviin": 2, "hahmota": 1, "suunnitella": 1, "hankalaa": 2, "sanat": 1, "suoraviivaisia": 2, "vastakohtana": 1, "tutummista": 1, "concept-image": 1, "opetusta": 1, "toisaalta": 7, "kyseisest\u00e4": 4, "n\u00e4k\u00f6kulmia": 1, "f\u00f6rfattare": 1, "3jokseenkin": 1, "puhuva": 1, "silja": 3, "n\u00e4iden": 7, "sisun": 1, "association": 1, "t\u00e4sm\u00e4llisen": 2, "teksti\u00e4": 2, "raja": 1, "itsek\u00e4\u00e4n": 1, "opiskelijoita": 3, "laiden": 1, "sosiaalisten": 1, "kursseista": 1, "tunnelatausta": 1, "v\u00e4likokeesta": 4, "parvon": 1, "kenties": 1, "l\u00e4hinn\u00e4": 5, "lukualueiden": 1, "laskeminen": 1, "tutkimuslaitos": 1, "melkein": 1, "oikeasti": 1, "yli": 2, "heikkoon": 1, "sanoin": 2, "monimutkaiselta": 1, "kulkevat": 1, "esimerkkej\u00e4": 4, "matematiikassa": 15, "t\u00e4ydent\u00e4\u00e4": 2, "jolla": 1, "lis\u00e4t\u00e4": 2, "pariin": 1, "ilmeet": 1, "luultavasti": 1, "vertailtu": 1, "2006": 12, "lausekkeen": 1, "ratkaisemisessa": 1, "opiskeltaessa": 1, "samanlaista": 1, "sis\u00e4lt\u00f6": 2, "v\u00e4is\u00e4nen": 1, "toiselle": 1, "samansuuntaisia": 1, "totesin": 1, "p\u00e4\u00e4see": 1, "sivuaineryhm\u00e4t": 1, "tutkimuskysymykset": 3, "uskomukset": 3, "j\u00e4sent\u00e4\u00e4": 2, "r066": 1, "tyypillisi\u00e4": 2, "ty\u00f6kaluna": 1, "sis\u00e4llytt\u00e4\u00e4": 4, "tarvittavat": 2, "yksikk\u00f6\u00e4": 1, "luotua": 1, "pohditaan": 3, "yliopistomatematiikkaan": 6, "huomio": 1, "further": 1, "asenteet": 2, "heille": 2, "l\u00e4sn\u00e4": 2, "v\u00e4lineit\u00e4": 1, "merkkin\u00e4": 1, "kuulumista": 1, "olleilla": 1, "k\u00e4ytt\u00e4v\u00e4t": 3, "opettamista": 1, "k\u00e4sitteellisen": 1, "ratkaisunsa": 4, "harjoittelevan": 1, "saattavat": 1, "r\u00e4m\u00f6": 2, "korrektien": 1, "swear": 1, "tavoitteita": 3, "hyv\u00e4\u00e4": 1, "vaikutuksesta": 1, "lukiosta": 2, "erikoissanastoa": 1, "korvaamaan": 1, "yhteispistem\u00e4\u00e4r\u00e4n": 2, "in": 16, "tahansa": 3, "n\u00e4k\u00f6kulmista": 1, "poikkeavat": 1, "kyselylomaketta": 2, "power": 1, "helpottamaan": 1, "ainakin": 6, "juurikaan": 1, "rekisterin": 3, "n\u00e4": 1, "opiskelutovereidensa": 1, "perspectives": 2, "alkioihin": 1, "osuus": 3, "n\u00e4kee": 1, "konventionaalinen": 1, "arviointien": 1, "hallita": 1, "yhdistelemist\u00e4": 1, "oppimista": 2, "vaan": 9, "luokan": 2, "palauttanutta": 1, "itsest\u00e4\u00e4n": 2, "helsingin": 10, "what": 1, "kielest\u00e4": 3, "ainoastaan": 1, "symbolikieli": 2, "henkil\u00f6it\u00e4": 1, "kumppaneiden": 4, "critique": 1, "strategiatiedon": 2, "muistaa": 1, "pikemminkin": 1, "ilmauksia": 1, "osaa": 4, "ct": 1, "vastauspapereihin": 1, "mutta": 39, "leen": 1, "raportoi": 1, "k\u00e4ytt\u00e4v\u00e4ns\u00e4": 1, "tilaisuus": 1, "sternberg": 3, "vaikeitakin": 2, "heikot": 2, "leikki\u00e4": 1, "ulkopuoliselle": 2, "b-kohta": 1, "making": 1, "joukoksi": 1, "kielelt\u00e4": 1, "lomakekysely": 4, "olemassa": 2, "vahvempia": 1, "kaikki": 22, "korrelaatiokertoimella": 1, "yhdistetty": 1, "matemaatikko": 2, "mielek\u00e4s": 1, "perustelutavoista": 1, "v\u00e4hemm\u00e4n": 2, "mik\u00e4\u00e4n": 1, "ylioppilastutkintolautakunta": 1, "vuosina": 2, "jaon": 1, "nimess\u00e4": 1, "pituuden": 1, "menestymisen": 4, "vaikutus": 1, "huonoiksi": 1, "keywords": 1, "teoksessa": 12, "silius": 1, "toistaiseksi": 3, "esimerkkipisteytykset": 1, "johtop\u00e4\u00e4t\u00f6ksens\u00e4": 2, "tapauksissa": 1, "ensimm\u00e4isten": 1, "ep\u00e4formaaliin": 1, "tyyppiin": 1, "virheellisesti": 1, "erikseen": 3, "harjoitusteht\u00e4vien": 3, "12015": 1, "matematiikkaansa": 1, "ty\u00f6kalupakkiin": 1, "kommunikoida": 1, "mediaani": 1, "selitt\u00e4miseen": 1, "kuvaamista": 1, "r\u00e4m\u00f6lle": 1, "lis\u00e4ys": 1, "place": 1, "melko": 6, "luonnolliselle": 4, "monenlaisissa": 1, "finnish": 1, "transition": 2, "helsinki": 1, "ty\u00f6tavaksi": 1, "pintapuolisesti": 1, "pelkk\u00e4\u00e4": 1, "ep\u00e4selvyyksi\u00e4": 1, "oivalluksiin": 1, "otin": 1, "ainedidaktiikan": 1, "sallittuja": 1, "tapahtumaan": 1, "lauseoppinsa": 1, "muutamia": 1, "ep\u00e4todeksi": 1, "ymm\u00e4rretyksi": 1, "my\u00f6ten": 1, "t\u00e4m\u00e4ntyyppisten": 1, "osaalueittain": 1, "aiheutuu": 1, "paperille": 3, "koulussa": 1, "palata": 1, "tampereella": 1, "kielent\u00e4misteht\u00e4v\u00e4t": 18, "saatuun": 1, "erilaisten": 3, "joukko-oppia": 1, "oppilaista": 1, "l\u00e4p\u00e4isemiseen": 1, "kurssituloksiin": 1, "todistustekniikoita": 1, "kirjoittamaan": 2, "tarvittaessa": 3, "insin\u00f6\u00f6rimatematiikan": 1, "puhtaan": 1, "piirre": 1, "eroon": 1, "p\u00e4\u00e4tell\u00e4": 4, "tukena": 2, "tarkastelu": 1, "tarkoitettiin": 1, "k\u00e4ytt\u00e4mist\u00e4": 1, "konseptuaaliseen": 2, "varten": 8, "konteksteista": 1, "toteuttaessaan": 1, "kuulumattomat": 1, "matemaattiset": 3, "oletettavasti": 1, "nimet": 1, "vastaamatta": 1, "saamiseen": 1, "esitys": 1, "hy\u00f6dynt\u00e4nyt": 1, "arvostelussa": 1, "kirjoitettuun": 2, "mak": 1, "lis\u00e4pistett\u00e4": 2, "h\u00e4nen": 3, "k\u00e4ytetty": 7, "p\u00e4\u00e4aineopiskelijat": 1, "kohtaan": 5, "jakautuminen": 7, "sotkeentua": 1, "matematiikka": 16, "koska": 9, "symbolein": 1, "ilmaistaan": 1, "esitell\u00e4\u00e4n": 12, "yliopistokontekstissa": 1, "l\u00f6ytyy": 1, "vaiheiden": 1, "v\u00e4liss\u00e4": 1, "aluksi": 5, "monet": 1, "\u00e4idinkielen\u00e4": 1, "0\u20135": 1, "kehottaa": 1, "puhuessaan": 2, "how": 1, "vahvasti": 3, "turhan": 1, "kokonaispistem\u00e4\u00e4r\u00e4n": 1, "teachers": 2, "conference": 1, "erotuksen": 3, "l\u00e4p\u00e4ist\u00e4kseen": 1, "tehnyt": 1, "nro": 8, "luonnontieteilij\u00f6iden": 1, "toimineelta": 1, "kielent\u00e4misteht\u00e4v\u00e4st\u00e4": 1, "laskettujen": 1, "tietokoneella": 1, "k\u00e4\u00e4nn\u00f6kse": 1, "istuu": 2, "mallit": 2, "n\u00e4k\u00f6inen": 1, "pyrkiv\u00e4t": 2, "formalismiin": 1, "representations": 1, "kev\u00e4\u00e4n": 2, "piirteet": 1, "45-54": 1, "chronaki": 3, "eroja": 3, "mukautuvan": 1, "k\u00e4ytt\u00e4minen": 3, "kysytty": 1, "valitsin": 1, "ep\u00e4formaalin": 2, "publishers": 1, "m\u00e4\u00e4r\u00e4": 1, "tutkimuksella": 1, "laatimaan": 2, "arviointity\u00f6ss\u00e4": 1, "kehitetty": 1, "writing": 5, "lukion": 5, "kuitenkin": 24, "institution": 1, "antavat": 1, "viiteen": 2, "pieni": 2, "empiirisest\u00e4": 1, "johdanto": 2, "esitt\u00e4m\u00e4\u00e4n": 2, "rekisteri": 3, "k\u00e4dess\u00e4": 1, "etsint\u00e4": 3, "menetelm\u00e4": 1, "2007": 7, "piirteit\u00e4": 3, "menestymist\u00e4": 1, "hillsdale": 1, "conceptual-embodied": 1, "halusin": 1, "helposti": 4, "vaikuttaa": 5, "mielenkiintoa": 1, "kyselylomakkeella": 2, "termien": 4, "tyypillisimm\u00e4t": 1, "yll\u00e4olevissa": 1, "ongelmiinsa": 1, "onnistua": 1, "kaksisuuntaista": 1, "vaihtoehto": 1, "kaikesta": 1, "toteutusta": 1, "sopivimman": 1, "ilmaisisin": 1, "tekemist\u00e4": 1, "77\u201390": 1, "pisteisiin": 1, "ilmaisutavoissa": 1, "proceedings": 2, "pohjalla": 3, "kartoitettiin": 5, "standardimallin": 3, "ruuasta": 1, "ihanteellista": 1, "oppilaidensa": 1, "mitattujen": 1, "perusvalmiuksien": 2, "harjoittelevalle": 1, "symbolikielelt\u00e4": 1, "esitetty": 23, "v\u00e4ltell\u00e4": 1, "kertomusmalli": 1, "millaista": 1, "pisteytysesimerkkej\u00e4": 1, "k\u00e4yt\u00f6n": 2, "\u201cjoukkojen": 1, "pisteytyst\u00e4": 2, "ilmaisua": 5, "leikkaamiseen": 1, "k\u00e4\u00e4nn\u00f6steht\u00e4v\u00e4": 2, "p\u00e4\u00e4sem\u00e4\u00e4n": 1, "muodostivat": 1, "kysymys": 1, "paikalla": 1, "pikakirjoitusmaisesti": 1, "kappaleissa": 1, "k\u00e4sialaan": 1, "k\u00e4\u00e4nnett\u00e4ess\u00e4": 2, "vastauksia": 8, "kielent\u00e4misteht\u00e4viss\u00e4": 6, "muotoilee": 2, "kielent\u00e4misteht\u00e4vien": 20, "v\u00e4liset": 1, "esitelty": 1, "osoittajasta": 1, "seulan": 1, "nuoli": 1, "sanallisia": 2, "etsit\u00e4\u00e4n": 1, "kirjoitti": 4, "opetellessa": 1, "avautuvat": 1, "370\u2013371": 1, "auttavan": 3, "numerosta": 1, "ansio": 1, "routledge": 2, "toimivilta": 2, "alkaen": 1, "pidet\u00e4\u00e4n": 1, "college": 1, "tulevana": 1, "osuvasti": 1, "virhek\u00e4sitysten": 1, "osassa": 1, "233\u2013243": 1, "t\u00e4ytt\u00e4m\u00e4\u00e4n": 1, "ylioppilaskokeita": 1, "tarjoama": 1, "1632016": 1, "olisikin": 1, "toimivuus": 1, "tavallisessa": 1, "aineiston": 12, "kertovat": 1, "tieteenalana": 1, "mittari": 1, "yhteiskunta": 1, "derivaattaan": 1, "opiskelijalla": 1, "olevansa": 2, "rasti": 1, "n\u00e4ki": 1, "lihavointi": 1, "vuodesta": 1, "panostettu": 2, "samankaltaisten": 1, "aineisto": 4, "tyypillisesti": 2, "vieraannuttaa": 1, "kirjoittamisen": 3, "tarpeita": 1, "yhdistelem\u00e4ll\u00e4": 1, "ristiriitaisia": 1, "pohtia": 3, "muodossa": 1, "omaava": 1, "k\u00e4siteltiin": 1, "t\u00e4llaisia": 1, "t\u00e4rkeist\u00e4": 1, "arviointiohjeita": 1, "jo": 5, "tiivist\u00e4": 3, "aikoo": 1, "ristiriidassa": 2, "studies": 2, "ilmoittautui": 2, "york": 1, "ymm\u00e4rsiv\u00e4t": 1, "haastavaa": 1, "olevien": 1, "likiarvoa": 1, "alkuvaiheessa": 5, "erlbaum": 1, "kokemuksestani": 1, "laskutaidot": 1, "pystyv\u00e4t": 1, "pitkin": 1, "kielent\u00e4minen": 28, "anxiety": 1, "puolestaan": 15, "kumppanit": 2, "lis\u00e4pisteiden": 2, "tutkittavista": 1, "36\u201339": 1, "p\u00e4\u00e4asiallinen": 1, "1t\u00e4ysin": 1, "s\u00e4hk\u00f6inen": 1, "kertomusmallissa": 1, "yritt\u00e4v\u00e4t": 1, "laati": 1, "tunnistaminen": 1, "ymm\u00e4rt\u00e4m\u00e4ksi": 1, "additional": 1, "yksin\u00e4\u00e4n": 1, "oppilasta": 1, "v\u00e4livaiheet": 3, "tapahtui": 1, "1\u20133": 3, "tyyli": 1, "v\u00e4ltt\u00e4m\u00e4tt\u00e4": 10, "lihapullaa": 1, "esseiden": 1, "keskihajonnan": 1, "merkint\u00f6": 1, "tavaksi": 1, "ero": 1, "k\u00e4sitteellis-ruumillinen": 1, "havainto": 1, "viimeisess\u00e4": 1, "edet\u00e4": 1, "kyseinen": 2, "onkin": 5, "opintojen": 1, "tehokkaasti": 1, "sukunimen": 1, "huolellisemmin": 1, "vaikeimmaksi": 1, "urakeskeisemp\u00e4\u00e4": 1, "enint\u00e4\u00e4n": 2, "osallistua": 2, "johon": 4, "montana": 1, "m\u00e4\u00e4r\u00e4ytyi": 1, "luvussa": 10, "iso-britanniassa": 1, "aloittavalle": 1, "lainkaan": 1, "symbolikielelle": 1, "adu-gyamfi": 1, "vaatii": 3, "\ud835\udc65\ud835\udc65\u2208\ud835\udc34": 1, "yl\u00e4kerran": 1, "opitaan": 1, "reflektoimaan": 1, "mediaa": 1, "kielenkaltaisia": 1, "tekstin": 5, "tutkituista": 1, "suuri": 5, "yht\u00e4l\u00e4isyyksi\u00e4": 2, "arvaamalla": 1, "esimerkin": 1, "opettamiseen": 1, "ollut": 3, "2p": 8, "opelinjan": 1, "uusintatutkimuksessa": 1, "termej\u00e4": 3, "kirjoitettuja": 2, "tilalla": 2, "vastaaminen": 2, "fysiikkaa": 1, "tavalla": 8, "lotta": 1, "liittyvi\u00e4": 13, "pohjalta": 3, "n65": 1, "hitaalta": 1, "kokeisiin": 1, "jotkut": 3, "t\u00e4m\u00e4ntyyppisest\u00e4": 1, "oikkoselle": 1, "teht\u00e4v\u00e4st\u00e4": 21, "sanallisiin": 1, "kieliteoreettinen": 1, "oppituntien": 1, "toimia": 2, "k\u00e4sittelev\u00e4\u00e4n": 1, "k\u00e4sitteille": 1, "johtuu": 3, "2001": 10, "\ud835\udc65\u221220": 1, "kielen": 40, "visible": 1, "joiden": 6, "kyseiseen": 1, "osanottajasta": 1, "httpwwwedimensioficontentflipped-learning-e28093lc3a4c3a4ke-matematiikan-opiskelun-motivaatio-ongelmiin": 1, "erottelukyky\u00e4": 1, "kommunikaatio": 1, "ajattelunsa": 1, "3\u201315": 1, "k\u00e4\u00e4nn\u00f6steht\u00e4vien": 1, "2011": 7, "vastaa": 2, "bn": 3, "kolme": 3, "testi\u00e4": 3, "menetelm\u00e4opetuksen": 1, "negatiivista": 1, "kerrokseen": 1, "vastausta": 3, "kielent\u00e4misteht\u00e4v\u00e4": 12, "\u201clingo": 1, "opettaessaan": 1, "loppuarvosanaa": 2, "vertailla": 1, "kielellisesti": 3, "tiiviydest\u00e4": 1, "ilmaisun": 19, "osaksi": 1, "saattaisivat": 1, "ongelman": 2, "yliopistomatematiikkaa": 1, "kieliopillisesti": 4, "k\u00e4ytt\u00f6tavan": 1, "jonkinlaiset": 1, "kuvailemaan": 2, "riippuvuuksien": 1, "taitavampia": 1, "voivat": 7, "kahdella": 1, "salakieleksi": 1, "\u201cosoita": 1, "aiheuttaa": 4, "tuntuisi": 1, "ty\u00f6l\u00e4st\u00e4": 1, "teht\u00e4v\u00e4orientoituneen": 1, "my\u00f6t\u00e4": 1, "esitt\u00e4miseen": 1, "opiskelemaan": 1, "oinonen": 1, "siirtymiseen": 1, "kuromaan": 1, "hyv\u00e4ll\u00e4": 1, "alkiot": 8, "vet\u00e4ytymiseen": 1, "ylsi": 1, "oleva": 2, "vaikeuksiin": 1, "vapaaehtoista": 2, "suhtautuivat": 2, "turku": 1, "tutkijalla": 1, "mahdollistaa": 1, "esitetyist\u00e4": 1, "n\u00e4enn\u00e4isest\u00e4": 1, "pinnallisesti": 1, "erityiskiitokset": 1, "t\u00e4sm\u00e4lliseen": 1, "analysis": 1, "co": 1, "selvi\u00e4\u00e4": 1, "edustaa": 1, "sek\u00e4": 64, "knowledge": 2, "sujuvahko": 1, "muodostavat": 4, "kokonaisuudesta": 2, "viestint\u00e4\u00e4n": 1, "tekem\u00e4ss\u00e4": 1, "p\u00e4\u00e4ttely\u00e4": 1, "opinnoissaan": 1, "omaan": 1, "kielent\u00e4mistaitonsa": 1, "ratkaisujen": 6, "kuinka": 3, "ohjaajilleni": 1, "tarkasteltaessa": 3, "matemaattiseksi": 1, "huono": 1, "rohkaisee": 1, "tuleva": 1, "hautala": 3, "korvattiin": 1, "yhteispisteiden": 1, "tapahtuu": 2, "ratkaisija": 6, "lukujen": 1, "research": 4, "poissulkeva": 2, "level": 1, "vaadittiin": 1, "joukko-opilliset": 1, "havaittiin": 5, "uudesta": 1, "itse\u00e4\u00e4n": 3, "esitystapaan": 1, "toteuttamiseen": 1, "laskea": 1, "mielikuvat": 1, "ep\u00e4selv\u00e4\u00e4": 1, "s\u00e4ilytyspaikka": 1, "construction": 1, "er\u00e4s": 9, "kohdatessaan": 1, "k\u00e4ytt\u00e4m\u00e4\u00e4": 2, "reliabiliteettia": 1, "mukaansa": 3, "saada": 11, "olennaisten": 1, "tekstiin": 1, "mielt\u00e4minen": 1, "lukea": 3, "vanhoihin": 1, "valtaosin": 1, "ilmet\u00e4": 1, "jonkin": 7, "huolellisesti": 1, "suhtautuvista": 1, "bss\u00e4": 1, "self-efficacy": 1, "liittyen": 1, "kohtaavat": 1, "kunkin": 6, "toiseen": 4, "laadittuja": 1, "education": 8, "menneisyytt\u00e4": 1, "rappuset": 1, "tekij\u00f6it\u00e4": 1, "osa-alueilla": 1, "yksisuuntaista": 2, "koodinvaihto": 2, "osattu": 1, "opettajaa": 1, "rajata": 1, "maksimipistem\u00e4\u00e4r\u00e4": 3, "paul": 1, "tehneist\u00e4": 1, "helpoiksi": 1, "v\u00e4itteill\u00e4": 2, "luennot": 1, "arvelee": 2, "ker\u00e4tty\u00e4": 1, "max": 2, "lukevalle": 1, "hankaliakin": 1, "pisteet": 4, "oppimistaan": 1, "kirjoitusurakan": 1, "numero": 3, "l\u00e4hestymistavan": 1, "perusteluja": 3, "ajatusmallista": 1, "teht\u00e4v\u00e4\u00e4n": 2, "analysoinnissa": 3, "lomaketta": 1, "supistamiseen": 1, "lis\u00e4\u00e4": 3, "piirtein": 1, "sama": 7, "virheett\u00f6mi\u00e4": 2, "arvioinnista": 1, "s\u00e4hk\u00f6isess\u00e4": 1, "kehitt\u00e4mi\u00e4": 1, "ilmi\u00f6iden": 1, "pisteist\u00e4": 1, "algoritmien": 1, "teoreettiseen": 1, "ty\u00f6tapana": 5, "omassa": 1, "mielipiteit\u00e4": 2, "ilmaisut": 1, "kerrotaan": 1, "voisivat": 2, "kolmannessa": 1, "mahdotonta": 2, "tottunut": 1, "erilaisiin": 1, "ohjelmaa": 1, "tiiviit\u00e4": 2, "konseptuaalisessa": 1, "kulttuurillisia": 1, "vain": 15, "matemaattista": 11, "sallimaan": 1, "omia": 1, "kuviokieleen": 1, "vieraan": 1, "sanojen": 1, "vaihtelevia": 1, "liittyiv\u00e4t": 2, "opetettavaa": 2, "arvioitavat": 1, "sis\u00e4llysluettelo": 1, "yl\u00f6nen": 1, "ensimm\u00e4iseen": 2, "sopivaksi": 1, "procedural": 2, "seuraavassa": 4, "1042016": 1, "kiinnostavaa": 1, "nature": 1, "eroaa": 2, "nuorta": 1, "lukiomatematiikassa": 1, "seurauksena": 1, "t\u00e4rke\u00e4": 2, "hyv\u00e4n": 2, "muksikselle": 1, "koodinvaihtoteht\u00e4v\u00e4ss\u00e4": 1, "yliopiston": 15, "tutkittaville": 2, "hy\u00f6ty\u00e4": 6, "poiki": 1, "ottamatta": 1, "kehitt\u00e4\u00e4": 2, "n\u00e4hden": 2, "arvioitiin": 4, "kyselyn": 4, "kutsutaan": 1, "nimitykset": 2, "hallitsevat": 1, "k\u00e4ytt\u00f6\u00e4": 6, "erilaisilla": 1, "sopivan": 2, "korkeakouluopiskelijoille": 1, "t\u00e4ydennysteht\u00e4v\u00e4t": 3, "opettajana": 2, "opettaminen": 2, "opetuksen": 5, "painottuen": 1, "nousevat": 1, "icmi": 1, "enimm\u00e4ism\u00e4\u00e4r\u00e4": 1, "kyll\u00e4sty\u00e4": 1, "sanotulla": 1, "herk\u00e4sti": 1, "tuloksissa": 1, "pojat": 1, "kielent\u00e4misteht\u00e4v\u00e4tyypit": 1, "henkil\u00f6\u00e4": 1, "sin\u00e4ns\u00e4": 2, "k\u00e4ytt\u00e4misen": 1, "olettaa": 2, "tapaansa": 1, "kuvaa": 5, "laaja": 1, "luonnontiedett\u00e4": 1, "mieluisaa": 1, "syv\u00e4llist\u00e4": 1, "kielenk\u00e4yt\u00f6ss\u00e4": 1, "osaaminen": 3, "monitulkintaisuuksia": 2, "koepisteiden": 6, "\u201con": 1, "ainedidaktiikat": 1, "k\u00e4ytt\u00f6": 2, "induktioteht\u00e4v\u00e4": 1, "suora": 3, "kurssikokeissa": 1, "vakiintuneessa": 2, "p\u00e4\u00e4llekk\u00e4isi\u00e4": 1, "nyckelord": 1, "johtavan": 2, "teht\u00e4v\u00e4": 30, "muillakin": 2, "sille": 3, "vastauksen": 5, "ty\u00f6skentelytilaksi": 1, "1987": 2, "tehtyjen": 1, "tulos": 1, "kyvyt": 1, "newman": 2, "tavalliseen": 1, "poistamiseen": 1, "nardin": 1, "mielt\u00e4": 10, "365\u2013378": 1, "katsoessa": 1, "jyv\u00e4skyl\u00e4": 4, "eritasoisten": 1, "ajattelussa": 1, "maa": 1, "tasapaino": 1, "ep\u00e4johdonmukaisuutta": 1, "olennainen": 1, "diplomity\u00f6ss\u00e4\u00e4n": 1, "ensimm\u00e4isest\u00e4": 6, "kulttuurin": 1, "v\u00e4lill\u00e4": 15, "k\u00e4sitteet": 1, "useampaa": 2, "valkoisella": 3, "hallintaa": 1, "pidemm\u00e4lle": 1, "lukijalle": 1, "yksil\u00f6": 1, "merkitsi": 1, "n\u00e4yttiv\u00e4t": 1, "kriteerit": 12, "vainio": 2, "kognitiivisen": 1, "n\u00e4ihin": 1, "3a": 2, "ilmaista": 4, "kykenev\u00e4ns\u00e4": 1, "entisest\u00e4\u00e4n": 1, "k\u00e4\u00e4nt\u00e4minen": 3, "l\u00f6yt\u00e4minen": 1, "joitakin": 2, "tobias": 2, "liittyvist\u00e4": 1, "vaikutusta": 2, "samankin": 1, "nimityksell\u00e4": 1, "syksyn": 1, "tunnistettavia": 1, "virta": 1, "kis\u00e4llioppiminen": 1, "luennoille": 1, "kielent\u00e4mistapa": 1, "oikea": 1, "laskemista": 1, "mahdollistavaa": 1, "ryhmitell\u00e4": 1, "selvent\u00e4\u00e4": 2, "h\u00e4m\u00e4t\u00e4": 1, "technology": 1, "tarvinnut": 1, "prosenttiin": 1, "kiinnostavia": 1, "merkint\u00f6ineen": 1, "helpoilta": 2, "pisteytyksest\u00e4": 1, "188\u2013196": 1, "yksinkertaisuudestaan": 1, "kokevat": 3, "lukiossa": 3, "rengas": 1, "tiettyyn": 2, "k\u00e4\u00e4nn\u00f6styyppisiin": 1, "voi": 24, "k\u00e4yt\u00f6st\u00e4": 1, "tietysti": 1, "mediaaniarvo": 1, "ty\u00f6kaluja": 1, "kysely": 3, "mitk\u00e4": 1, "aiheuttavat": 1, "mukaisesti": 3, "erityyppiset": 1, "lis\u00e4siv\u00e4t": 2, "toteavat": 1, "associates": 1, "rh": 1, "society": 1, "ii-kohdassa": 3, "ty\u00f6n": 3, "selityksi\u00e4": 1, "joutunut": 2, "palauttamaan": 1, "olennaisia": 1, "aiempien": 2, "reittej\u00e4": 1, "preparation": 1, "kommenttimalli": 2, "vastaajilla": 1, "sellaista": 5, "vastaavasti": 2, "aiheen": 1, "sanamuotojen": 1, "tyyppisen": 1, "odotteluun": 1, "oppivan": 1, "undergraduate": 1, "kognitiotiede": 1, "per\u00e4\u00e4n": 1, "ty\u00f6kalu": 2, "suuret": 1, "im": 2, "v\u00e4hennettiin": 2, "koskevat": 1, "kielent\u00e4misen": 15, "gradu": 5, "symbolikielt\u00e4": 11, "hyv\u00e4ksi": 1, "v\u00e4hennyksi\u00e4": 2, "ole": 25, "k\u00e4sitteit\u00e4": 4, "sukupuolioletuksen": 1, "tarkastellaan": 4, "suullinen": 2, "ilmaisemista": 1, "v\u00e4itt\u00e4m\u00e4n": 2, "titel": 1, "havaittuani": 1, "pakko": 1, "kielent\u00e4v\u00e4": 1, "selityst\u00e4": 6, "ensiksi": 2, "v\u00e4hiten": 1, "interactions": 1, "sis\u00e4llytti": 1, "case": 1, "oppilas": 6, "esitet\u00e4\u00e4n": 1, "korrelaatiokertoimen": 3, "k\u00e4yt\u00f6ss\u00e4": 6, "ajatusta": 1, "maailmassa": 3, "k\u00e4ytt\u00e4v\u00e4": 1, "kieless\u00e4": 2, "formaalia": 1, "puolelta": 1, "teht\u00e4viss\u00e4": 4, "madallettu": 1, "sitten": 2, "persoonallinen": 1, "roolissa": 2, "arnold": 1, "hyl\u00e4t\u00e4\u00e4n": 1, "kuilun": 1, "niiss\u00e4": 5, "sekoittua": 1, "kis\u00e4llimetodin": 1, "arvon": 2, "enimm\u00e4ispistem\u00e4\u00e4r\u00e4": 1, "ilmaisullisilla": 1, "aloittelevalla": 1, "fysiikka": 1, "merkill\u00e4": 1, "ja": 413, "todistettavan": 1, "aletaan": 1, "korrelaatiokerroin": 1, "riipu": 1, "nelj\u00e4nnes": 1, "curriculum": 1, "pukemaan": 1, "tarkastella": 2, "laskulausekkeissa": 1, "ansaita": 1, "plain": 1, "eastern": 1, "oppilaille": 5, "erillisell\u00e4": 1, "uusia": 2, "title": 1, "proseduraalinen": 1, "ymm\u00e4rret\u00e4\u00e4n": 1, "teaching": 5, "ymm\u00e4rt\u00e4misen": 1, "71\u201386": 1, "tuottanut": 1, "4(1": 1, "muilla": 3, "a-kohdasta": 2, "subjektiivisia": 1, "s\u00e4\u00e4nn\u00f6nmukaisuuksia": 2, "kaventaminen": 1, "assosioi": 1, "oppimistavoitteita": 1, "tarkemman": 1, "\u00f6vriga": 1, "pystyn": 1, "hy\u00f6dyllisi\u00e4": 4, "sit\u00e4": 31, "8\u201315": 1, "t\u00e4ytt\u00e4m\u00e4tt\u00e4": 1, "itsekin": 1, "korrelaatio": 12, "kuvan": 4, "laadinnassa": 1, "taas": 5, "fysiikan": 1, "sis\u00e4ltyy": 6, "tulevaisuudessa": 1, "91(5": 1, "boss\u00e9": 1, "hirvonen": 1, "kriteerin": 3, "ymm\u00e4rryksen": 1, "nyt": 3, "k\u00e4sitelt\u00e4v\u00e4t": 1, "kolmella": 1, "s\u00e4\u00e4nt\u00f6j\u00e4": 1, "kohdistaa": 1, "algoritminen": 1, "ensisijaisesti": 3, "pyydettiin": 3, "perusasioihinkin": 1, "kannustaa": 1, "merkint\u00f6jen": 3, "teetettiin": 1, "kutsuisi": 1, "graduaan": 1, "mit\u00e4": 11, "viittaavan": 1, "laskutoimitusten": 1, "kirjallisuudessa": 1, "humanities": 1, "oivallinen": 1, "k\u00e4yt\u00e4nn\u00f6ksi": 1, "luokanopettajien": 1, "usiskin": 7, "prosesseja": 1, "k\u00e4\u00e4nn\u00f6s": 2, "sis\u00e4ll\u00f6n": 1, "kokonaisia": 11, "rauhallisessa": 1, "kahteen": 5, "ratkaisussa": 4, "useimmilla": 1, "kirjoitetaan": 1, "symbolit": 6, "ajattelusta": 2, "matematiikalla": 2, "opetuksensa": 1, "kiitokset": 2, "matikassakin": 1, "kieli\u00e4": 1, "koottu": 1, "matemaattisilla": 1, "annettu": 3, "vett\u00e4": 1, "merkint\u00e4": 1, "tutkimuskysymyksiin": 2, "mittaustulosten": 1, "hissiin": 1, "osana": 1, "matemaattiseen": 8, "sijoittuivat": 1, "ylip\u00e4\u00e4ns\u00e4": 2, "yll\u00e4mainittu": 1, "kev\u00e4t": 1, "kaasila": 1, "eiv\u00e4t": 21, "vieras": 1, "t\u00e4sm\u00e4llisess\u00e4": 1, "faulconer": 1, "p\u00e4\u00e4ss\u00e4ni": 2, "puoliksi": 1, "kahden": 7, "lukuun": 1, "xt": 1, "k\u00e4sin": 1, "n\u00e4ist\u00e4": 5, "k\u00e4ytt\u00e4miseen": 2, "kaipaisivat": 1, "kuvatun": 1, "joissa": 2, "virkkeist\u00e4": 1, "kuhunkin": 1, "joutuu": 3, "konsepti": 2, "tarkoittavat": 1, "mccormick": 2, "rakenteet": 1, "ohjaamaan": 1, "kurssitunnusta": 1, "systemaattisen": 1, "t\u00e4m\u00e4n": 17, "ratkaisun": 6, "tekiv\u00e4t": 5, "h\u00e4n": 8, "poikkeavia": 1, "p\u00e4\u00e4dyn": 1, "kokemuksia": 1, "yksil\u00f6imisen": 1, "ottaen": 1, "american": 2, "algoritmiseen": 1, "ohjaajana": 1, "arkip\u00e4iv\u00e4isist\u00e4": 1, "olleet": 4, "v\u00e4lille": 4, "opiskellessaan": 1, "kehittyneemp\u00e4\u00e4": 1, "ratkaisumalli": 2, "anonyymina": 1, "matemaattisten": 4, "saatua": 1, "age": 1, "a-kohta": 2, "mets\u00e4muuronen": 6, "kirjaimellisesti": 1, "matkaa": 1, "tekem\u00e4ns\u00e4": 1, "motivaatiota": 1, "tietoarkisto": 1, "paperia": 1, "maidenhead": 1, "koululuokassa": 1, "gradun": 1, "suhteellisen": 2, "pisteytettiin": 3, "k\u00e4sitys": 3, "tekij\u00e4ns\u00e4": 1, "hy\u00f6dyist\u00e4\u00e4n": 1, "sellaiset": 2, "arkiel\u00e4m\u00e4st\u00e4": 1, "kohtalainen": 3, "sanastonsa": 1, "m\u00e4\u00e4ritelm\u00e4t": 1, "tuttua": 1, "mihin": 1, "englanniksi": 1, "sukupuolistereotypioiden": 1, "ansainnut": 1, "formal": 1, "puutteen": 1, "author": 1, "hersh": 3, "viitataan": 1, "otolle": 1, "taito": 1, "likert-asteikolla": 2, "olla": 15, "meaning": 1, "bias": 1, "kustakin": 3, "esim": 6, "tied\u00e4n": 1, "pyrkii": 1, "ker\u00e4tyn": 2, "lukuisia": 1, "lomakekyselyst\u00e4": 1, "mediaanin": 1, "b72": 1, "huomioitu": 1, "positiiviset": 1, "tai-sanaa": 1, "tekem\u00e4\u00e4n": 6, "toinen": 7, "sai": 17, "avulla": 21, "kokonaislukujen": 1, "opettaa": 1, "nollahypoteesi": 1, "tarkasteltavat": 1, "osaamistaan": 1, "ihmisi\u00e4": 1, "koetusta": 1, "ohjaajina": 1, "jaollisuuden": 2, "leikkaamisena": 1, "ongelmanratkaisua": 1, "havaittu": 4, "merkint\u00f6j\u00e4": 9, "v\u00e4lineen\u00e4": 1, "matematiikkakuilua": 2, "sis\u00e4ltyi": 2, "vaikeampia": 1, "ensimm\u00e4isell\u00e4": 1, "assa": 1, "merkint\u00e4\u00e4": 1, "aikana": 5, "reflektoivan": 2, "ilmaisullinen": 1, "teht\u00e4v\u00e4nanto": 2, "ojanen": 3, "m\u00e4\u00e4rittely": 1, "n\u00e4kyvi\u00e4": 1, "kirjoittaneet": 2, "methelp": 1, "laajemmin": 2, "kielen\u00e4": 3, "sukupuoli": 2, "kriteerej\u00e4": 1, "sanallisessa": 1, "open": 1, "sis\u00e4ll\u00e4": 1, "saattaa": 8, "turhalta": 1, "noss": 2, "tekem\u00e4t": 1, "patterns": 1, "suomalainen": 1, "teht\u00e4v\u00e4tyypeiss\u00e4": 1, "kielent\u00e4miseen": 13, "alkion": 1, "menetelm\u00e4t": 1, "httpswikihelsinkifipagesviewpageactionpageid154151863": 1, "6(3": 1, "laittamalla": 1, "vastasivat": 1, "mukaisia": 1, "vastauksissa": 4, "kuljettaakseen": 1, "vastannut": 1, "oxford": 1, "436\u2013441": 1, "sarikan": 1, "aiemmissa": 3, "reflektoida": 1, "matematiikasta": 8, "k\u00e4sitteisiin": 1, "suhde": 1, "contexts": 1, "report": 2, "aloittamaan": 1, "vastauksessa": 3, "istu": 1, "an": 4, "vastaus": 5, "tietoja": 2, "tutkielman": 1, "mainitut": 2, "voida": 11, "kaksi": 9, "pakollinen": 1, "palautti": 5, "osoittautuivat": 1, "kontekstiksi": 2, "liikaa": 1, "ohjausta": 1, "kuluttaa": 1, "osaamiseen": 2, "hallinta": 1, "ongelmaan": 1, "suoraan": 2, "n\u00e4kyviin": 1, "parantua": 1, "tietoon": 2, "l\u00e4p\u00e4isiv\u00e4t": 1, "lukeminen": 1, "virheelliset": 1, "antamien": 1, "yhteenlaskuna": 1, "suoran": 1, "ehto": 1, "kokonaisuuksiin": 1, "ett\u00e4": 108, "kolmas": 4, "ensimm\u00e4ist\u00e4": 1, "selitt\u00e4minen": 6, "alkuvaiheen": 5, "2014": 7, "sijasta": 1, "pitk\u00e4ss\u00e4": 1, "tekemisell\u00e4": 2, "k\u00e4sitteellis-ruumiillinen": 1, "malleista": 1, "valtaosan": 1, "0p": 11, "olevaan": 1, "tutkimuksissa": 3, "vastataan": 1, "yhteydess\u00e4": 8, "algoritmista": 1, "symboleista": 1, "liittyv\u00e4t": 5, "kumpulan": 1, "k\u00e4sityst\u00e4": 1, "v\u00e4itt\u00e4miin": 1, "k\u00e4ytti": 4, "kirjoittamisesta": 1, "from": 2, "keskusteleva": 1, "bkohdan": 1, "new": 1, "tarkoitetaan": 5, "kolmeen": 1, "laadittiin": 4, "pieni\u00e4": 2, "mallia": 1, "parantamiseksi": 1, "selkeit\u00e4": 1, "communication": 4, "voidaanko": 1, "tutkimuksen": 26, "selkeimpi\u00e4": 2, "relaatioita": 1, "6\u201346": 1, "puhuttuna": 1, "kautta": 3, "tarkoita": 1, "k\u00e4sity\u00f6tieteeseen": 1, "p\u00e4\u00e4aineopiskelijolle": 1, "ottamaan": 1, "tehdyt": 1, "heikommilla": 1, "tiedostaa": 2, "sosiaalista": 1, "tarkoituksena": 1, "rakennetta": 1, "todistusta": 1, "kommunikoimisen": 1, "r\u00e4s\u00e4nen": 1, "kysymyksiss\u00e4": 1, "kaikkia": 3, "tulee": 11, "lukeminenkaan": 1, "kuvailee": 1, "palauttamista": 2, "k\u00e4\u00e4nt\u00e4misteht\u00e4v\u00e4ss\u00e4": 1, "liian": 2, "kirjoitan": 4, "lukemista": 3, "p-arvolla": 1, "tilanteeseen": 1, "vaivaton": 1, "suuressa": 1, "sallimia": 2, "joutuvani": 1, "ilmaisussa": 1, "tuesta": 1, "ominaisuuksiin": 1, "koulutuksessa": 1, "aikaavievyyden": 1, "juha": 1, "p-arvon": 1, "hy\u00f6tyj\u00e4": 2, "pe": 1, "keskeisten": 1, "sanalla": 1, "lausekkeessa": 1, "tyyppi\u00e4": 1, "nimitt\u00e4j\u00e4st\u00e4": 1, "ep\u00e4formaalisti": 1, "tarkoitetulla": 1, "kemian": 1, "kemia": 1, "arviointikriteerej\u00e4": 1, "syvemmin": 1, "pyydetyn": 1, "lahdenper\u00e4": 1, "psychology": 1, "ilmaisuja": 3, "osalle": 1, "tutkijat": 1, "b-kohtaa": 1, "teht\u00e4v\u00e4tyyppej\u00e4": 1, "opettajaopiskelijoiden": 1, "olisikaan": 1, "t\u00e4rkeiksi": 1, "ymm\u00e4rr\u00e4": 2, "selke\u00e4t": 1, "asiat": 2, "matikkap\u00e4\u00e4t\u00e4": 1, "ei-matemaattiseen": 1, "perustana": 1, "valitaan": 1, "osateht\u00e4v\u00e4\u00e4n": 1, "opintojensa": 1, "tutkimusotos": 2, "suomen": 6, "pois": 6, "2812016": 1, "selke\u00e4\u00e4n": 1, "synnynn\u00e4isest\u00e4": 1, "tulla": 1, "keskittyv\u00e4t": 1, "merkitse": 1, "kirjallisessa": 1, "yliopistossa": 3, "asteen": 1, "my\u00f6nt\u00e4v\u00e4sti": 1, "luonnollisella": 4, "helppoa": 2, "vastaukseen": 4, "proseduraaliseen": 2, "kielteisesti": 2, "muutamat": 1, "t\u00e4ysin": 8, "oppia": 1, "huomioineet": 1, "mj": 2, "kuuden": 1, "315\u2013332": 1, "opiskelijasta": 1, "kokivat": 3, "tunnistetietoina": 1, "tulkinnassa": 2, "vektorin": 1, "venn-diagrammilla": 1, "tutkimuksessani": 1, "tiivistelm\u00e4": 1, "vaativissa": 1, "sillanrakennusty\u00f6kalu": 1, "1997": 3, "menetelmien": 1, "t\u00e4ydennysteht\u00e4v\u00e4": 2, "hakivatko": 1, "lukum\u00e4\u00e4r\u00e4": 4, "kangas": 1, "kaksinkertaiset": 1, "tekstiss\u00e4": 3, "millaisia": 4, "tuntui": 1, "tullen": 1, "tilastollisesti": 2, "hajontaa": 1, "k\u00e4ytt\u00e4m\u00e4\u00e4n": 5, "apprenticeship": 2, "l\u00e4\u00e4ke": 1, "neuvoa": 1, "kirjoitettuna": 1, "kirjoittivat": 1, "kielent\u00e4m\u00e4\u00e4n": 1, "monenlaisia": 2, "kirjoittamista": 1, "uskon": 2, "l\u00e4p\u00e4isi": 1, "kuvaileminen": 1, "seuraava": 1, "pidemm\u00e4n": 1, "muokattiin": 2, "tai-sanan": 2, "tulevassa": 2, "vastaan": 2, "min\u00e4k\u00e4sitys": 1, "jouduttu": 1, "symbolisten": 1, "tutkittavaa": 2, "2012": 4, "tietenkin": 3, "opettajien": 5, "ne": 18, "tutkijoiden": 1, "kiinnostuneita": 1, "riippuvia": 1, "kurkistaa": 1, "osaamisen": 3, "p\u00e4tevyytt\u00e4": 2, "k\u00e4\u00e4nsi": 1, "hankaluuksia": 1, "tueksi": 1, "kutsua": 2, "niin": 12, "eteenp\u00e4in": 1, "kokonaisella": 1, "pelkist\u00e4mist\u00e4": 1, "proseptuaalis-symbolinen": 1, "kielent\u00e4\u00e4": 1, "graafinen": 1, "p\u00e4\u00e4asiassa": 2, "\ud835\udc5d005": 1, "v\u00e4likokeen": 8, "k\u00e4ytett\u00e4ess\u00e4": 2, "hallitsi": 3, "malinen": 1, "kokeiden": 1, "luotettavuutta": 4, "yhdistiv\u00e4t": 2, "esityst\u00e4": 1, "vaativat": 1, "k\u00e4sittelev\u00e4t": 1, "menestys": 1, "edelleen": 2, "aloilla": 1, "mukana": 3, "ulkopuolelta": 1, "oikeiden": 3, "virheett\u00f6m\u00e4n": 1, "642016": 1, "yliopistoopintojen": 1, "ratkaisuperiaatteen": 1, "joihin": 1, "kuitenkaan": 6, "norton": 1, "kielenk\u00e4yt\u00f6n": 2, "tehneet": 3, "muissa": 2, "opiskelee": 1, "omasta": 3, "social": 3, "maailmasta": 1, "alas": 1, "monimutkaisti": 1, "t\u00e4ytetty": 2, "sis\u00e4lt\u00e4vi\u00e4": 2, "tutkia": 2, "kyse": 1, "yksinkertaisella": 1, "aloittelevilla": 1, "erotettiin": 2, "1p": 28, "graduprosessin": 1, "k\u00e4rsiv\u00e4llisyytt\u00e4": 1, "tuottivat": 1, "kognitiotiedett\u00e4": 1, "useammalla": 1, "ilmenev\u00e4t": 1, "vastaako": 1, "oikein": 1, "kyselyss\u00e4": 1, "ryhmien": 1, "useampikin": 1, "harjoitusteht\u00e4viin": 1, "k\u00e4yt\u00e4v\u00e4": 1, "k\u00e4yttiv\u00e4t": 2, "syy-seuraussuhdetta": 1, "vaikeaa": 4, "kulju": 2, "kontekstina": 1, "metakognitiot": 1, "tiedostamattaankin": 1, "jatkuvassa": 1, "tarkkaan": 2, "yksil\u00f6n": 2, "tietty": 2, "\ud835\udc35\u2216\ud835\udc34": 1, "paljon": 11, "laskutoimitukset": 2, "v\u00e4hent\u00e4\u00e4": 3, "periaatteeseen": 1, "kielten": 4, "hoyles": 6, "pelk\u00e4st\u00e4\u00e4n": 3, "tapansa": 1, "opiskelu": 4, "j\u00e4rjest\u00e4m\u00e4ll\u00e4": 1, "arviointi": 9, "tyypillinen": 1, "t\u00e4rke\u00e4ss\u00e4": 1, "tarpeeksi": 4, "hy\u00f6dynt\u00e4mist\u00e4": 1, "joh\ud835\udc4e\u2208\ud835\udc34": 1, "avointa": 1, "hallussa": 3, "jaettu": 1, "2010": 22, "ainetta": 1, "rekisteri\u00e4": 1, "muodostamista": 1, "mukaisesta": 1, "t\u00e4ytt\u00f6\u00f6n": 1, "pelk\u00e4n": 1, "collins": 2, "tossavainen": 5, "k\u00e4sitykseen": 1, "kis\u00e4llioppimisessa": 1, "nimett\u00f6myydest\u00e4": 1, "luomiseen": 1, "englannin": 1, "gender": 1, "olisin": 1, "tilanteesta": 1, "a-kohtaan": 1, "resursseja": 1, "standardimallinen": 1, "merkitseminen": 1, "p0001": 3, "ohjaillaan": 1, "saa": 2, "derivoidaan": 1, "synty\u00e4": 1, "edenneill\u00e4": 1, "maailmaan": 3, "monien": 1, "httpshelkalinneanetficgibinpwebreconcgibbid2373793": 1, "ratkaisu": 5, "selitt\u00e4\u00e4": 4, "722003": 1, "aloittavien": 2, "taustasta": 1, "449\u2013458": 1, "murtolausekkeisiin": 1, "mielest\u00e4si": 2, "rakentaa": 1, "perusteella": 9, "tutkittavaksi": 1, "kis\u00e4llioppimisen": 6, "siit\u00e4": 16, "etteiv\u00e4t": 1, "vs": 1, "pyyt\u00e4v\u00e4n": 1, "year": 1, "aiheesta": 1, "alkioita": 1, "uudelleenkirjoittamisen": 1, "opetuskokeilussa": 1, "opinn\u00e4ytet\u00f6it\u00e4": 1, "laskuharjoituksiin": 2, "ensiarvoisen": 1, "voisiko": 1, "merkityksen": 2, "kirjoitustyyliin": 1, "v\u00e4itt\u00e4m\u00e4\u00e4n": 1, "joltakulta": 1, "aiempaan": 2, "n68": 1, "vertaistuesta": 1, "harjaannuttaa": 1, "kirjoituksia": 1, "p\u00e4\u00e4st\u00e4": 2, "luonnolliseen": 2, "todistaa": 1, "osanottajista": 4, "koulutuksen": 1, "tarpeellista": 1, "ymm\u00e4rt\u00e4\u00e4": 9, "as": 2, "oleville": 2, "arviointikriteerit": 9, "ben-zeev": 1, "yhdist\u00e4minen": 1, "ajatella": 2, "ymm\u00e4rrett\u00e4viss\u00e4": 1, "luottamuksen": 1, "kirjoittavat": 1, "alkuoletusten": 1, "commission": 1, "palauttaneiden": 1, "laajentumisena": 1, "t\u00e4ydensi": 1, "yhdistelm\u00e4": 1, "tulokset": 10, "t\u00e4ydennysteht\u00e4v\u00e4st\u00e4": 2, "through": 2, "extreme": 1, "\ud835\udc34\u2216\ud835\udc35": 3, "tavoitematriisilla": 1, "hahmotteleva": 1, "ilmeni": 1, "esimerkkien": 1, "\ud835\udc65\u00b1": 1, "rovaniemell\u00e4": 1, "opiskelijalle": 4, "p\u00e4\u00e4asiallisesti": 1, "selitt\u00e4m\u00e4\u00e4n": 1, "prosessoida": 1, "kielennettyihin": 1, "yrj\u00f6nsuuren": 1, "selkeytt\u00e4m\u00e4\u00e4n": 1, "method": 1, "suurempi": 1, "viitattu": 5, "nousi": 1, "aikamuotoja": 1, "faculty": 1, "kuuluu": 3, "kurssitunnus": 1, "ettei": 3, "pistem\u00e4\u00e4r\u00e4\u00e4n": 2, "teht\u00e4vist\u00e4": 4, "arvioijalle": 1, "maksimissaan": 2, "kysymyksen": 2, "hyv\u00e4ksynn\u00e4n": 1, "tallin": 4, "m\u00e4\u00e4ritelt\u00e4viin": 1, "uskoakseni": 2, "kurssin": 46, "p\u00e4\u00e4dyin": 1, "suhtautumistaan": 1, "symboli-ilmaisua": 1, "viittaakin": 1, "l\u00e4ht\u00f6kohtana": 2, "mielenkiintoisesta": 1, "rajattu": 1, "oppilailtaan": 1, "kyselyosuuden": 1, "muuttaa": 2, "saaduilla": 1, "vahvoja": 1, "valmistavia": 1, "p\u00e4\u00e4osin": 2, "information": 2, "uppgifter": 1, "laitoksen": 3, "nieminen": 1, "t\u00e4ydennysteht\u00e4v\u00e4ss\u00e4": 1, "tutkiessaan": 1, "m\u00e4\u00e4r\u00e4llisen": 1, "tuttuus": 1, "j\u00e4rjestetty": 1, "puute": 1, "mahdollisia": 1, "hy\u00f6dytt\u00e4isi": 1, "lauseet": 2, "ilmaisee": 2, "ominaisia": 1, "rajauksen": 1, "korkeakaan": 1, "sivuaineena": 1, "fakultet": 1, "10\u201320": 1, "kielent\u00e4misell\u00e4": 4, "ymm\u00e4rt\u00e4mist\u00e4": 2, "kielent\u00e4misteht\u00e4v\u00e4\u00e4": 5, "sovellettiin": 1, "olennaista": 2, "ylimp\u00e4\u00e4n": 1, "tutkimani": 1, "kohdassa": 2, "vahva": 1, "m\u00e4\u00e4r\u00e4tty": 1, "osoittamaan": 1, "sijaan": 3, "teht\u00e4vien": 20, "yksil\u00f6llisi\u00e4": 1, "omien": 2, "huolimatta": 7, "\u201chaluaisin": 1, "lienev\u00e4t": 2, "kev\u00e4\u00e4ll\u00e4": 3, "voimakasta": 1, "lahjakkuudesta": 1, "havaitsemaan": 1, "teki": 1, "johtaa": 3, "koettuja": 1, "matematiikkaan": 2, "standardimallia": 1, "n\u00e4k\u00f6kulmana": 1, "tehostetun": 5, "_________________": 1, "aivan": 4, "opiskelevia": 1, "nua": 1, "lis\u00e4vahvistusta": 1, "student": 1, "hallidayn": 1, "romu": 1, "and": 19, "keino": 2, "valita": 2, "selkokielell\u00e4": 1, "pit\u00e4v\u00e4t": 3, "challenging": 2, "menestymisell\u00e4": 1, "j\u00e4iv\u00e4t": 1, "riippuen": 2, "kuvittelisin": 1, "v\u00e4\u00e4rink\u00e4sityksiin": 1, "kuvien": 5, "september": 1, "teht\u00e4v\u00e4variaatioita": 1, "erityispiirteens\u00e4": 1, "loput": 1, "laadullisessa": 1, "koemenestykseen": 1, "kokeillen": 1, "yhteytt\u00e4": 5, "ihanteita": 1, "prosenttia": 2, "ongelmanratkaisukurssin": 1, "sy\u00f6m\u00e4\u00e4n": 1, "ihan": 1, "ik\u00e4\u00e4n": 1, "toisella": 3, "pro": 6, "hallitseva": 1, "v\u00e4itteet": 7, "halliday": 2, "ilmaisupisteiden": 15, "miten": 16, "reports": 1, "tietoverkkona": 1, "n\u00e4it\u00e4": 3, "l\u00e4helle": 1, "jaossa": 3, "ajatuksen": 1, "pakenemaan": 1, "vaikeampi": 1, "instruction": 1, "toisin": 1, "oivalluksen": 1, "valinnassa": 1, "t\u00e4ss\u00e4": 20, "\ud835\udc5d0001": 1, "ajatuksenkulkua": 1, "atematiikkapdf": 1, "kriteerist\u00e4": 6, "opiskelijoilta": 6, "tuottavien": 1, "\ud835\udc34\u222a\ud835\udc35": 3, "h\u00e4iritsev\u00e4": 1, "opettajankoulutuslaitoksen": 1, "hy\u00f6dynt\u00e4en": 1, "kulku": 1, "sekoittaa": 1, "yliopisto-opinnot": 3, "\u00e4lyllist\u00e4": 1, "vaikeuksia": 5, "p\u00e4invastoin": 3, "riippuu": 2, "jaollisten": 1, "conceptual": 2, "tehostetussa": 1, "rutinoiduttua": 1, "menetelm\u00e4tietoa": 1, "poissulkevana": 1, "kappaletta": 1, "kuviin": 1, "hyv\u00e4n\u00e4": 1, "koodinvaihtoa": 2, "kesken\u00e4\u00e4n": 6, "yhteispistem\u00e4\u00e4r\u00e4\u00e4": 1, "asia": 2, "bandura": 2, "hy\u00f6dyllisen\u00e4\\n\\nt\u00e4ss\u00e4": 1, "ryhm\u00e4ty\u00f6skentelyyn": 1, "iap": 1, "niiss\u00e4kin": 1, "v\u00e4linen": 2, "leikattiin": 2, "merkitsevyystasoja": 1, "kuvaamaan": 1, "eroa": 3, "aloitetaan": 1, "kehotuksen": 2, "mainiosti": 2, "olisiko": 1, "lukijan": 2, "vastanneista": 1, "k\u00e4si": 1, "muut": 2, "analysointi": 2, "osaajilta": 1, "opiskelumotivaatioon": 1, "yhdistettyn\u00e4": 1, "vaikuttivat": 1, "havaita": 4, "ahonen": 1, "vaikeuksien": 1, "huikkola": 1, "muodostaa": 2, "reading": 1, "kuva": 40, "opintoihin": 1, "kokonaispisteiden": 1, "yksitt\u00e4isiin": 1, "pienempiin": 1, "ajatusty\u00f6n": 2, "pilottitutkimus": 1, "kokonaisuutta": 1, "pistejakauma": 2, "vaihdella": 1, "analyysi": 2, "opettajalle": 2, "annetun": 1, "tuntenut": 1, "syntyv\u00e4st\u00e4": 1, "t\u00e4llaiset": 1, "motivoimaan": 1, "v\u00e4lilt\u00e4": 1, "osaajan": 1, "tavoitematriisi": 1, "todistamisesta": 1, "p\u00e4\u00e4aineenaan": 1, "ihminen": 1, "er\u00e4\u00e4lt\u00e4": 1, "nelj\u00e4nnen": 5, "antamia": 1, "puutteellinen": 1, "kyseisten": 1, "liitteet": 2, "toim": 12, "vanhojen": 1, "ymm\u00e4rrett\u00e4vi\u00e4": 9, "hankalana": 1, "koeaika": 1, "jakautumista": 1, "muotoiltuja": 1, "arvoja": 1, "yliopistomatematiikassa": 1, "paikkaansa": 1, "sortui": 1, "tekem\u00e4ll\u00e4": 6, "leikkaus": 3, "t\u00e4ll\u00e4": 5, "js": 1, "kiinnostaa": 1, "noin": 4, "matematiikkajumpalla": 1, "ohjeita": 1, "varmemmin": 1, "abstraktiin": 1, "ihmetell\u00e4": 1, "kiinnostavampia": 1, "selkeytt\u00e4miseksi": 1, "ilmaisusta": 1, "sanallisesta": 2, "etsittiin": 2, "symbolikieleksi": 1, "todistamista": 1, "pyrit\u00e4\u00e4n": 4, "tuloksista": 2, "symboliesityksess\u00e4": 2, "3\u20137": 1, "perustelutaitojen": 1, "ratkaisuv\u00e4lineen\u00e4": 1, "sana": 2, "sanallisiksi": 1, "yhdest\u00e4": 1, "ongelmakohdat": 1, "c-kohdassa": 1, "laskutapa": 1, "menestyminen": 2, "osuessa": 1, "tiekarttamallin": 1, "opintopisteen": 1, "keskityt\u00e4\u00e4n": 1, "kh168": 1, "mahdollisiksi": 1, "yksiselitteisesti": 1, "kolmesta": 2, "ajatus": 2, "merkint\u00e4tapoja": 2, "ajatellaan": 1, "pohtimiseen": 1, "tarkennuksia": 3, "k\u00e4ytet\u00e4\u00e4n": 5, "ohjelmoinnissa": 1, "varmasti": 3, "saaneilla": 3, "across": 1, "tutkiminen": 2, "mielest\u00e4ni": 8, "sellaisia": 2, "donmukaisesti": 1, "joissain": 1, "n\u00e4kyy": 1, "saatavilla": 3, "yh\u00e4": 1, "noudattavat": 1, "p\u00e4\u00e4se": 2, "tehd\u00e4": 2, "turhauttavaksi": 1, "itseisarvo": 1, "sarakkeessa": 1, "kokonaispistem\u00e4\u00e4r\u00e4\u00e4n": 1, "ainoa": 3, "nctm": 2, "he": 13, "falmer": 1, "testattaisiin": 1, "laajalla": 1, "n\u00e4kyv\u00e4ksi": 2, "kielent\u00e4misteht\u00e4v\u00e4tyyppej\u00e4": 3, "lyhyen": 2, "tulosten": 1, "arvioijien": 1, "omin": 2, "palautukset": 1, "er\u00e4\u00e4nlainen": 1, "november": 1, "aineistosta": 1, "k\u00e4velylenkeist\u00e4": 1, "onnistuivat": 1, "toisesta": 1, "parempiin": 1, "vaatimuksesta": 1, "kuulumattomiin": 1, "saamastani": 1, "taulumuistiinpanot": 1, "kysy\u00e4": 4, "29\u201333": 1, "reaalilukuihin": 1, "painottuva": 1, "havaittaville": 1, "esiintyv\u00e4t": 1, "luonnontieteilij\u00e4t": 1, "painos": 1, "ryhm\u00e4\u00e4n": 1, "axiomatic-formal": 1, "t\u00e4ytett\u00e4v\u00e4ksi": 1, "periaatteella": 1, "suhtautumista": 1, "k\u00e4sitteen": 2, "tapausta": 1, "tekem\u00e4tt\u00e4": 1, "merkint\u00f6ihin": 1, "number": 1, "lukeneisiin": 1, "matematiikkakuilu": 2, "arvioija": 1, "havaittavissa": 3, "gates": 1, "helppo": 2, "opetuksessa": 5, "ohjeistus": 1, "luokassa": 2, "helppoja": 1, "asioita": 5, "speaking": 1, "abstract": 1, "n\u00e4iss\u00e4": 1, "yliopisto-opinnoissa": 1, "tyyppisen\u00e4": 1, "arvioineet": 1, "vai": 3, "jyv\u00e4skyl\u00e4n": 1, "ohjeet": 1, "lopulta": 2, "merkitt\u00e4v\u00e4": 2, "malli": 2, "nyky\u00e4\u00e4n": 1, "laaditut": 2, "kielent\u00e4misteht\u00e4v\u00e4ss\u00e4": 1, "oikeat": 2, "esitettyj\u00e4": 1, "matematiikkakuilun": 2, "vaikka": 12, "english": 1, "kolmijako": 1, "n\u00e4hd\u00e4kseni": 1, "introducing": 1, "opinnot": 1, "vaaka-akselilla": 1, "pysy\u00e4": 1, "v\u00e4lineet": 1, "perusteet": 1, "saadun": 1, "koodinvaihtoteht\u00e4v\u00e4t": 1, "teknillinen": 3, "kirjoittanut": 2, "kohdalle": 2, "joskus": 3, "itsetunto": 1, "olivat": 11, "t\u00e4ydet": 5, "usiskinin": 2, "aksiomaattis-formaali": 2, "1995": 2, "mate": 1, "teoreettista": 1, "tilanne": 2, "teett\u00e4misest\u00e4": 1, "sidoantal": 1, "tutkimustulokset": 1, "symboleilla": 1, "beyond": 1, "opinnoissa": 2, "ilmaisupisteeseen": 1, "esitt\u00e4misess\u00e4": 3, "totesi": 2, "seikka": 1, "h\u00e4hki\u00f6niemi": 1, "saaneiden": 8, "oliko": 2, "kontekstista": 2, "ruutuun": 1, "aineiden": 2, "kvalimotv": 1, "positiivinen": 6, "tutkimus": 7, "math": 2, "laatia": 3, "tiedekirjasto": 1, "ratkaisuun": 6, "k\u00e4\u00e4nsiv\u00e4t": 1, "sormunen": 1, "aiempaa": 1, "oli": 50, "pyydett\u00e4isiin": 1, "t\u00e4m\u00e4": 20, "samankaltaisia": 3, "valikoiman": 1, "luontevaa": 2, "esimerkkiteht\u00e4v\u00e4t": 1, "tutkittavan": 1, "symboliseen": 1, "\u00e4idinkielell\u00e4": 1, "muotoon": 2, "\u00e4kki\u00e4": 1, "taulukoissa": 1, "ideoiden": 1, "yksil\u00f6intiin": 1, "joukkoerotuksesta": 2, "silloin": 3, "prosepti": 1, "k\u00e4ytt\u00e4nyt": 1, "osin": 1, "oppimateriaaleja": 1, "pohjolainen": 2, "tutkimusraportti": 1, "molempia": 1, "prosentit": 1, "selke\u00e4sti": 5, "muutenkin": 1, "arvioinnissa": 9, "havainnoimisesta": 1, "kirjallisena": 1, "joista": 2, "pohdintaa": 2, "ymm\u00e4rt\u00e4neet": 2, "taitojen": 1, "kuviteltavissa": 1, "sis\u00e4lt\u00f6j\u00e4": 2, "johanna": 1, "puutteellisesti": 1, "suorittaneisiin": 1, "tueksikirjallinen": 1, "reflektoivaan": 1, "vastausesimerkist\u00e4": 1, "loppup\u00e4\u00e4telm\u00e4t": 1, "m\u00e4\u00e4rittelee": 2, "matematiikkaklinikoilla": 1, "kumpusi": 1, "usein": 11, "tunnettujen": 1, "toimi": 1, "ilmaisupisteit\u00e4": 6, "kuten": 15, "international": 5, "kriteereitt\u00e4in": 6, "j\u00e4\u00e4": 2, "muuten": 4, "ajatteluprosessiin": 1, "arbetets": 2, "verbimuotoon": 1, "termi\u00e4": 1, "t\u00e4ytt\u00e4\u00e4": 1, "erottelukyvyss\u00e4": 1, "merkitsevyystasot": 1, "poisj\u00e4\u00e4nnin": 1, "apuv\u00e4lineen\u00e4": 1, "kuuluvat": 3, "todistukseen": 1, "tutkimusp\u00e4iv\u00e4t": 1, "j\u00e4lkeen": 5, "opita": 1, "joukon": 7, "k\u00f6mpel\u00f6\u00e4": 1, "perustelujen": 4, "vastauksessaan": 3, "joukosta": 1, "ty\u00f6ns\u00e4": 1, "l\u00f6ytyvi\u00e4": 1, "paperilla": 1, "t\u00e4sm\u00e4llist\u00e4": 4, "p\u00e4iv\u00e4kirja": 1, "edell\u00e4": 5, "luonnollisista": 1, "1061": 1, "k\u00e4\u00e4nn\u00f6ksens\u00e4": 1, "arvot": 2, "voidaan": 27, "sekoittuminen": 1, "niiden": 16, "j\u00e4sent\u00e4misess\u00e4": 3, "osuutta": 1, "vastaustensa": 1, "kaikkien": 3, "ep\u00e4p\u00e4tev\u00e4ksi": 2, "a-level": 2, "geometriset": 1, "professori": 1, "arvosanajakauma": 1, "tarkoitus": 4, "selke\u00e4mmin": 1, "kriteeri": 26, "tekstist\u00e4": 2, "alkusanat": 1, "eroista": 1, "rekisteriin": 1, "ohjaajan": 5, "luvun": 1, "nimi": 2, "1\u201327": 1, "kielioppiin": 1, "saamat": 1, "mahdollisten": 1, "huolimattomuus": 1, "vastaajien": 5, "laskuharjoituksissa": 1, "lell\u00e4": 1, "toimisivatkin": 1, "hyl\u00e4t\u00e4": 1, "l\u00e4ro\u00e4mne": 1, "ratkaisuja": 5, "to": 3, "ohella": 1, "sanottavan": 1, "lukuohjeita": 1, "4t\u00e4ysin": 1, "kriteerist\u00f6\u00e4": 1, "esimerkki": 5, "annettiin": 2, "toimii": 1, "kontekstiin": 1, "2782015": 1, "aloilta": 1, "seoul": 1, "satoa": 1, "5-24": 1, "tappavat": 1, "ongelmakohtia": 1, "symbolikielen": 12, "yksitt\u00e4isten": 1, "arkikielest\u00e4": 2, "symbolikielest\u00e4": 2, "puitteissa": 1, "tarkkaa": 1, "hy\u00f6dynnet\u00e4\u00e4n": 1, "irrallisia": 1, "samansis\u00e4lt\u00f6iset": 1, "teen": 4, "tyypilt\u00e4\u00e4n": 1, "2004": 12, "joukoista": 1, "teht\u00e4viin": 3, "kiinnit\u00e4": 1, "oppimisprosessista": 1, "04\u2264|\ud835\udc5f|06": 1, "ahkerasti": 1, "konteksti": 2, "useitakin": 1, "laji": 1, "matemaatikon": 2, "kolmanneksi": 2, "k\u00e4\u00e4nnett\u00e4v\u00e4": 1, "classrooms": 1, "no": 1, "yliopistopedagogiikka": 1, "lukija": 2, "ytl": 1, "viiri": 1, "ohjaustilanteet": 1, "hallitsemaan": 1, "hallitse": 1, "ajattelun": 20, "kommentit": 1, "laitoksella": 2, "reaalimaailman": 2, "pisteeseen": 1, "rakennetaan": 1, "mukaan": 28, "parvo": 1, "osaamisesta": 1, "assessment": 1, "ty\u00f6tapa": 1, "tiivis": 2, "kovin": 6, "matemaattisen": 24, "ratkaisuperiaate": 1, "ohjaukseen": 7, "tukea": 4, "symbolikielisiin": 2, "saatiin": 2, "joukkoon": 4, "arviointiohjeet": 1, "v\u00e4likokeessa": 1, "arviointia": 1, "pit\u00e4en": 1, "silm\u00e4ll\u00e4": 1, "tarkistaminen": 1, "mahdollista": 13, "opetuksesta": 2, "asiantuntijuus": 1, "\u201cehdin": 1, "kirjoittamiseen": 2, "muodostamia": 1, "joidenkin": 1, "opiskelukavereiden": 1, "kutsuttua": 1, "kurssikoodia": 2, "muitakin": 2, "k\u00e4ytettyjen": 1, "muutamilla": 1, "suurta": 4, "arvioijalla": 1, "tilastollista": 1, "sellaiseksi": 1, "yksipuolista": 1, "aukon": 1, "\u00e4\u00e4rip\u00e4iss\u00e4": 1, "tutkielma": 2, "tuo": 1, "tietoisesti": 2, "datum": 1, "elementtej\u00e4": 1, "lopussa": 1, "kuusi": 1, "menestyiv\u00e4t": 1, "kuviokieli": 2, "lis\u00e4pisteit\u00e4": 1, "merkitys": 2, "ollen": 2, "useimmiten": 3, "ker\u00e4ttiin": 1, "elementeist\u00e4": 1, "taulukossa": 14, "tutkimukseni": 1, "merkit\u00e4": 1, "oppilaat": 4, "samalla": 3, "vastaajasta": 1, "t\u00e4rkeimpi\u00e4": 1, "sanoiksi": 1, "viel\u00e4": 10, "valossa": 1, "kerro": 1, "liites": 1, "kognitiotieteen": 1, "joukkoerotuksen": 1, "vastuulle": 1, "menestyst\u00e4": 1, "hy\u00f6dynt\u00e4\u00e4": 4, "j\u00e4sennetty\u00e4": 1, "ilmoittautujam\u00e4\u00e4r\u00e4st\u00e4": 1, "kieliaspekti": 1, "ratkaisua": 6, "vastineiksi": 1, "month": 1, "palauttaneista": 6, "selvent\u00e4v\u00e4n": 1, "hajonta": 3, "sopivuus": 1, "teht\u00e4v\u00e4ss\u00e4": 13, "kielent\u00e4mismallien": 1, "miss\u00e4": 5, "heikommin": 1, "poistettiin": 2, "2jokseenkin": 1, "v\u00e4liotsikoiden": 1, "jamison": 3, "robb": 1, "esiin": 1, "sis\u00e4lt\u00f6osaamisen": 1, "edess\u00e4": 1, "luontevasti": 1, "teacher": 2, "yhdistelev\u00e4st\u00e4": 1, "tulisi": 3, "kerrallaan": 2, "yl\u00e4puolella": 2, "el\u00e4v\u00e4sti": 1, "kokoamalla": 1, "flipped": 1, "p\u00e4\u00e4aineopiskelijoihin": 1, "istahtaa": 1, "tyhji\u00e4": 1, "osallistumista": 3, "k\u00e4ytt\u00e4\u00e4": 30, "kuvissa": 5, "negatiivinen": 4, "esimerkkin\u00e4": 1, "voinut": 1, "vaarassa": 1, "luotettavuustarkastelussa": 1, "ymm\u00e4rt\u00e4isiv\u00e4t": 1, "heti": 2, "saaneet": 6, "tilanteessa": 1, "l\u00e4mpim\u00e4t": 1, "m\u00e4\u00e4r\u00e4tyn": 1, "kontekstissa": 5, "k\u00e4ytt\u00e4j\u00e4st\u00e4": 1, "luonnollinen": 3, "laskutavan": 1, "yhdenmukaisuuteen": 1, "per\u00e4ti": 1, "ryhm\u00e4n": 1, "tuli": 5, "toimiva": 1, "tuottaa": 2, "saaranen-kauppinen": 3, "helpommin": 2, "oikeita": 11, "kahdeksan": 5, "vastaajista": 31, "korvaavia": 1, "esimerkkivastaus": 1, "k\u00e4y": 1, "poimimalla": 1, "vastaukset": 6, "v\u00e4livaiheita": 3, "vastauksella": 1, "lomakekyselyll\u00e4": 1, "monille": 1, "teht\u00e4v\u00e4lle": 2, "ajankohtaista": 2, "ajatukset": 2, "kanssa": 15, "samaksi": 1, "it": 1, "keskeinen": 1, "tietojenk\u00e4sittelytieteilij\u00f6it\u00e4": 1, "p\u00e4iv\u00e4kirjamallia": 1, "greenwich": 1, "aiheet": 1, "oppimistavoitteet": 1, "aika": 2, "1986": 4, "ty\u00f6kalut": 1, "muistuttavat": 1, "suurin": 10, "lauserakenteita": 1, "kyn\u00e4\u00e4": 1, "minua": 2, "kokee": 5, "esitt\u00e4m\u00e4t": 1, "ratkaista": 4, "t\u00e4sm\u00e4llisyyden": 1, "k\u00e4ytt\u00f6tapojen": 1, "osattiin": 1, "ilmoittautumisj\u00e4rjestyksen": 1, "oppimiseen": 2, "perusvalmiuksia": 1, "muuttuu": 1, "pa": 1, "seuraavaksi": 4, "pidett\u00e4v\u00e4lle": 1, "yksin": 2, "kyselylomakkeen": 3, "2015": 14, "taitavia": 2, "ttyn": 1, "selvill\u00e4": 1, "k\u00e4\u00e4nt\u00e4misest\u00e4": 1, "laajempia": 1, "huomioida": 1, "yksimielisi\u00e4": 1, "aiemmin": 2, "deposited": 1, "tehdess\u00e4\u00e4n": 1, "kokonaispisteist\u00e4": 1, "alustavat": 1, "nopeaa": 1, "tavoin": 6, "loppukysely": 1, "saatujen": 6, "tarvittavalle": 1, "vaikeaksi": 1, "abstraction": 1, "luentomateriaaleissa": 1, "monia": 1, "j\u00e4sentely\u00e4": 1, "p\u00e4rj\u00e4\u00e4v\u00e4ns\u00e4": 1, "kutakin": 1, "monthly": 1, "laitos": 9, "k\u00e4rsiv\u00e4llisyydest\u00e4": 1, "jatkossa": 1, "yliopistoissa": 2, "samaa": 6, "edellisess\u00e4": 1, "lineaarista": 1, "virhek\u00e4sityksi\u00e4": 1, "opetetun": 1, "johtop\u00e4\u00e4t\u00f6s": 3, "kriteerist\u00f6t": 1, "alkaa": 1, "tuntuivat": 2, "korreloivan": 2, "muistuttaa": 4, "ymm\u00e4rrett\u00e4v\u00e4\u00e4": 2, "ilman": 4, "ohjaajilta": 1, "l\u00f6ytyv\u00e4n": 2, "harjoitelleet": 1, "siirtyminen": 1, "sekoittaminen": 1, "lingo": 1, "k\u00e4\u00e4n-t\u00e4minen": 1, "selke\u00e4mm\u00e4lt\u00e4": 1, "tarjoa": 1, "monelle": 3, "keskustellut": 1, "kysymykseen": 2, "yearbook": 1, "kuvataan": 5, "pisteill\u00e4": 1, "vaikutti": 1, "lyhyesti": 1, "tulkinnanvaraisuuksia": 1, "k\u00e4ytt\u00e4neet": 1, "suorittaa": 3, "pc": 1, "esitystyyli": 1, "vaikuttiko": 1, "laatisin": 1, "kartoittavaan": 1, "for": 5, "poimiminen": 1, "tulkkaaminen": 2, "oppija": 1, "oikeaa": 2, "toisiinsa": 2, "yhdist\u00e4m\u00e4ll\u00e4": 1, "opettajat": 1, "of": 24, "jatkuva": 1, "harjoitusteht\u00e4vi\u00e4": 4, "kausaliteettia": 1, "yhdistyi": 1, "virheellisell\u00e4": 1, "objektiivisiksi": 1, "tutkitulta": 1, "matemaattisesta": 2, "t\u00e4llaisissa": 1, "puuttuvat": 1, "jotain": 2, "esitettiin": 1, "ylitt\u00e4v\u00e4t": 1, "edward": 1, "sanaparin": 1, "viereiseen": 1, "aiheutui": 1, "merkinn\u00e4t": 9, "7-811": 1, "toisen": 7, "negatiivisia": 1, "2003": 9, "edes": 2, "pellikka": 1, "t\u00e4t\u00e4": 4, "teht\u00e4v\u00e4nantomaiseen": 1, "suhteen": 2, "maalisti": 1, "kielent\u00e4misharjoittelua": 2, "kielenk\u00e4ytt\u00f6\u00f6ni": 1, "harjoitus": 1, "prosessissa": 1, "eri": 23, "teht\u00e4v\u00e4tyyppi\u00e4": 2, "t\u00e4sm\u00e4llisten": 1, "sanalliseen": 2, "syv\u00e4llisemp\u00e4\u00e4": 1, "nimett\u00f6m\u00e4n\u00e4": 1, "olivatko": 2, "havainnoimaan": 1, "v\u00e4it\u00f6skirja": 1, "perusopintoja": 1, "|\ud835\udc5f|\u226508": 1, "induktiotodistamiseen": 1, "saaduista": 1, "j\u00e4rjestetyn": 1, "oletetaan": 1, "ty\u00f6muotona": 1, "tulkittu": 1, "toteaa": 5, "v\u00e4littyy": 2, "kurssiin": 1, "na": 1, "otoskoko": 2, "painottunut": 1, "kysymyksiin": 3, "linacre": 1, "l\u00e4pi": 6, "hieman": 4, "yhteenlaskettu": 1, "v\u00e4list\u00e4": 3, "todistuksesta": 1, "p\u00e4\u00e4": 1, "saivat": 6, "opiskelun": 1, "ei": 67, "vahvan": 1, "keksien": 1, "perustaitotesteill\u00e4": 1, "negatiiviset": 1, "v\u00e4rik\u00e4st\u00e4": 1, "ep\u00e4tarkkuuksia": 1, "avusta": 1, "tarkastellut": 1, "\ud835\udc34\u2229\ud835\udc35": 2, "vallitsee": 1, "k\u00e4\u00e4nt\u00e4m\u00e4tt\u00e4": 1, "huomioiden": 1, "2005": 7, "oppijalle": 1, "asiasis\u00e4lt\u00f6jen": 1, "menetykseen": 1, "28(2": 1, "avaamaan": 1, "yhteiskuntatieteellinen": 1, "mik\u00e4li": 1, "positiivista": 1, "holum": 1, "kirjallisesta": 2, "muina": 1, "luovasti": 1, "selitetty": 2, "diskreetti": 1, "keskustelutilanteessa": 1, "lukioon": 2, "aloittelevana": 1, "aksioomien": 1, "tosin": 1, "ensin": 3, "merkki": 4, "tarkastelussa": 2, "vol": 2, "luettavaa": 1, "positiiviss\u00e4vyisi\u00e4": 1, "lasillisen": 1, "luento-opetusta": 2, "nimett\u00f6min\u00e4": 1, "teht\u00e4v\u00e4kokonaisuuksiin": 1, "kynnyst\u00e4": 1, "samoin": 2, "silloinkaan": 1, "vanhemmilta": 1, "ilmi\u00f6t\u00e4": 1, "sivuaineopiskelijoihin": 1, "taitotietoa": 1, "kyky\u00e4": 2, "taulukko": 14, "virkkeiden": 6, "hoylesin": 1, "valinnaiskurssilla": 1, "puhdas": 1, "opiskeluun": 3, "jt": 1, "niihin": 6, "matemaatikoiden": 1, "kirjalliseen": 1, "arvosanan": 1, "koulumatematiikasta": 1, "sivuaineopiskelijoista": 2, "osaan": 4, "kokeen": 4, "v\u00e4ltt\u00e4m\u00e4tt\u00f6m\u00e4n": 2, "tiedossa": 2, "mielekkyytt\u00e4": 3, "tukeutua": 1, "laajennuksena": 1, "esineist\u00e4": 1, "merkitsev\u00e4": 4, "opiskelijaa": 22, "joensuun": 1, "opinnoissani": 1, "joukko-operaatiot": 1, "tunnisteettomatkin": 1, "yliopisto-opiskelijat": 1, "lee": 6, "tiekartta": 1, "viikoittaisten": 1, "johtuvien": 1, "school": 2, "perusk\u00e4sitteit\u00e4": 1, "1998": 2, "mathematical": 8, "kohdista": 1, "r\u00e4\u00e4t\u00e4l\u00f6ity": 1, "hy\u00f6dynt\u00e4m\u00e4\u00e4n": 1, "keksittiin": 1, "selostetaan": 1, "kaavoja": 2, "ajattelutapojen": 1, "vastattiin": 1, "oppijana": 2, "t\u00e4ysist\u00e4": 1, "v\u00e4itteen": 9, "tavastasi": 1, "laskuharjoituksista": 1, "worlds": 1, "poikkeamia": 1, "luetaan": 1, "ks": 2, "lefevre": 4, "pohtimaan": 2, "national": 1, "tietynlaista": 1, "kiitt\u00e4\u00e4": 1, "algoritmisen": 1, "otetaan": 1, "tutkijatriangulaatiota": 1, "ty\u00f6kalulta": 2, "oppimisen": 5, "k\u00e4sitteiden": 5, "parhaimmillaan": 1, "july": 1, "muotoilut": 1, "yksitt\u00e4isiss\u00e4": 1, "yliopisto-opiskelijoilla": 1, "tampere": 3, "pearsonin": 2, "disciplines": 1, "supistaa": 1, "eli": 15, "n\u00e4e": 1, "kaltainen": 2, "kuvaava": 1, "pit\u00e4m\u00e4\u00e4n": 1, "psychologist": 1, "hyvi\u00e4": 2, "tosiel\u00e4m\u00e4ss\u00e4": 1, "nelj\u00e4\u00e4n": 2, "if": 1, "symbolilla": 3, "hy\u00f6dyllist\u00e4": 2, "harvempi": 1, "kunnes": 1, "kasvatus": 1, "luonnollisten": 1, "ilmaisuun": 1, "seassa": 1, "pisteiden": 3, "puhuen": 1, "mukainen": 1, "allekirjoittanut": 1, "erityisesti": 24, "millaisilla": 1, "keskusteluun": 1, "vikberg": 4, "v\u00e4itt\u00e4m\u00e4t": 1, "my\u00f6hemmin": 2, "yrj\u00f6nsuuri": 6, "ymm\u00e4rt\u00e4neen": 1, "taitavan": 1, "helpottaa": 1, "tauluty\u00f6skentelymallia": 1, "edustamien": 1, "universaaliksi": 1, "oppi": 1, "\u00e4idinkielen": 1, "pyritt\u00e4ess\u00e4": 1, "systemaattinen": 1, "kokoamisessa": 1, "positiivisesti": 4, "malleja": 1, "saaman": 1, "merkitty": 3, "a-kohtaa": 1, "oppimisprosessia": 1, "kohdalla": 4, "sis\u00e4ltyv\u00e4t": 1, "encounter": 1, "eteneminen": 1, "perehdyt\u00e4\u00e4n": 2, "lahdenper\u00e4n": 1, "n\u00e4hd\u00e4\u00e4n": 7, "ovat": 30, "lukiolainen": 1, "kaikkiaan": 2, "apuna": 1, "perustuu": 4, "117\u2013148": 1, "muuta": 3, "tekemien": 1, "pisteen": 8, "yhdisteest\u00e4": 2, "luonnollisesta": 2, "kenelle": 1, "excel-ohjelman": 2, "lis\u00e4tutkimusta": 2, "esiintyvi\u00e4": 1, "sarikka": 3, "tarkasti": 1, "valottaa": 1, "erilaista": 1, "tapahtuvasta": 1, "tahtiin": 1, "monen": 1, "tutkimustulosten": 1, "k\u00e4ytett\u00e4v\u00e4t": 4, "odotuksia": 1, "persoonatonta": 1, "oletukseen": 1, "kandidaattivaiheen": 1, "siis": 12, "puutteita": 3, "symbolikieleen": 1, "lomakekysely\u00e4": 1, "symboliesityksen": 1, "journal": 4, "l\u00e4heisesti": 1, "lajeista": 1, "yliopisto": 13, "toteutetussa": 1, "arvioitavan": 1, "taakse": 1, "esitti": 4, "luvut": 1, "virheellisi\u00e4": 3, "valmiin": 1, "educator": 1, "arvo": 1, "laadittujen": 1, "sivuaineopiskelijoiden": 1, "virheiden": 2, "erityinen": 1, "muuttujia": 2, "osallistumistaan": 1, "ratkaisuprosessia": 1, "kokonaan": 5, "kyselylomakkeeseen": 1, "abstraktimmiksi": 1, "mieleen": 1, "painetta": 1, "osaamisessa": 1, "marttila": 1, "tietovaranto": 1, "tapauksessa": 4, "ep\u00e4t\u00e4sm\u00e4llisyyksiin": 1, "kasvatustieteiden": 1, "taustaan": 1, "kirjoitetun": 1, "tarpeisiin": 1, "viiva": 1, "1322009": 1, "oman": 7, "b-kohdassa": 1, "pistem\u00e4\u00e4ri\u00e4": 1, "huhtikuu": 2, "k\u00e4ytettiin": 5, "laajuinen": 1, "p\u00e4\u00e4tytty\u00e4": 1, "validiteettia": 2, "opiskelija": 31, "varsinkin": 1, "kuuluvia": 1, "ty\u00f6l\u00e4\u00e4n\u00e4": 1, "etenev\u00e4t": 1, "tilastoty\u00f6kaluilla": 1, "practise": 1, "ajatteluun": 3, "suorana": 1, "asioille": 2, "v\u00e4h\u00e4isemp\u00e4\u00e4": 1, "ensimm\u00e4isess\u00e4": 1, "l\u00e4htem\u00e4ll\u00e4": 1, "n42": 1, "kyseess\u00e4": 1, "ajateltiin": 1, "\ud835\udc4e\u2209\ud835\udc34\u2216\ud835\udc35": 1, "liittyiv\u00e4tkin": 1, "tutkimusaineisto": 2, "merkkijonoja": 1, "takia": 2, "kunta": 1, "ty\u00f6ss\u00e4": 1, "kyselylomake": 4, "henkil\u00f6kohtaista": 1, "kurssimateriaalissa": 1, "tampereen": 7, "instituutti": 1, "httpswwwylioppilastutkintofiimagessivuston_tiedostotsahkoinen_tutkintofi_sahkoinen_m": 1, "joilla": 3, "esitettyihin": 1, "suunnilleen": 1, "kysymyksist\u00e4": 1, "henkil\u00f6m\u00e4\u00e4r\u00e4": 1, "esitystapa": 3, "todenn\u00e4k\u00f6isemp\u00e4\u00e4": 1, "rutinoituneiden": 1, "2009": 10, "prosessointia": 1, "tutkimusk\u00e4ytt\u00f6\u00e4": 1, "mielell\u00e4ni": 4, "liittiv\u00e4t": 1, "merkinn\u00f6ist\u00e4": 1, "jokaista": 2, "tilastollisten": 1, "jotta": 2, "tuottamista": 2, "ajatukseen": 1, "asiaksi": 1, "tilasto-ty\u00f6kaluilla\\n\\nopiskelijat": 1, "eik\u00e4": 11, "loppukyselyyn": 1, "taitoja": 4, "tukemaan": 1, "opiskelijan": 9, "ensimm\u00e4inen": 4, "asiaan": 1, "pyrin": 1, "arviointiin": 3, "n\u00e4hdess\u00e4\u00e4n": 1, "ylioppilastutkinto": 1, "joten": 11, "menetelmill\u00e4": 1, "merkilt\u00e4": 4, "ylioppilaskokeessa": 1, "p\u00e4\u00e4aineskaalalla": 1, "mahtuu": 1, "hy\u00f6dyksi": 1, "university-level": 1, "tiedekunnan": 1, "opettajia": 2, "irrationaaliluvut": 1, "sujuva": 3, "lauseiden": 1, "sanoa": 3, "3\u201348": 1, "kiinnitin": 1, "kokisi": 1, "tiloja": 1, "tarkoittavan": 1, "tarvittu": 1, "kielent\u00e4misest\u00e4": 6, "prosesseista": 1, "todeta": 2, "kokonaispisteet": 2, "liity": 1, "sotkeentuvista": 1, "saadut": 5, "nollaa": 1, "merkkien": 4, "vet\u00e4\u00e4": 1, "keskihajonta": 5, "\ud835\udc5d001": 1, "yht\u00e4\u00e4n": 2, "selitt\u00e4v\u00e4": 1, "toisentyyppisilt\u00e4": 1, "oma": 3, "sivuuttaa": 1, "opiskelijoilla": 5, "pelkki\u00e4": 2, "motivaatio-ongelmiin": 1, "korea": 1, "tiedekunta": 3, "keskiarvoksi": 1, "kielent\u00e4misharjoittelu": 4, "outoa": 1, "tehdess\u00e4ni": 1, "rakenne": 2, "merkkijonot": 1, "luotettavuus": 2, "kuin": 29, "sukupuolesta": 1, "k\u00e4ytt\u00e4misest\u00e4": 1, "muotoilussa": 1, "sanoista": 2, "kriteereiss\u00e4": 4, "peruskouluun": 2, "informaatio": 2, "vaikuttamaan": 1, "mahdollisessa": 1, "siin\u00e4": 3, "ymm\u00e4rrykselle": 1, "arvoinen": 2, "siksikin": 1, "ratkaisuissa": 5, "sopivaan": 1, "huolellisempaa": 1, "ilmaisupistett\u00e4": 5, "siirtym\u00e4": 1, "annetaan": 1, "kielelle": 5, "yliopisto-opetuksessa": 1, "osallistuminen": 3, "sanan": 6, "three": 1, "etenkin": 2, "toivola": 2, "eiv\u00e4tk\u00e4": 1, "loppuarvioinnin": 2, "kielent\u00e4misteht\u00e4v\u00e4n": 7, "selit\u00e4": 1, "kolmanteen": 3, "rotterdam": 1, "m\u00e4\u00e4r\u00e4tyille": 1, "soini": 1, "excel": 1, "p\u00e4hk\u00e4ileminen": 1, "opiskelijoista": 6, "saama": 1, "alareunaan": 1, "hahmottavatko": 1, "nardi": 3, "hallinnollista": 1, "k\u00e4sitt\u00e4\u00e4": 1, "ensinn\u00e4k\u00e4\u00e4n": 1, "tulkinnanvaraisuuksiin": 1, "liopillisesti": 1, "tutkimukseen": 2, "yhteens\u00e4": 5, "syv\u00e4llisemmin": 1, "selv\u00e4sti": 2, "j\u00e4tt\u00e4nyt": 2, "p\u00e4\u00e4tell\u00e4\u00e4n": 1, "koodinvaihtoteht\u00e4v\u00e4": 1, "siirtyess\u00e4\u00e4n": 1, "kuvauksia": 1, "informaatiota": 1, "you": 1, "jaettiin": 1, "k\u00e4sitykseens\u00e4": 1, "sanaksi": 2, "telun": 1, "selitettyjen": 1, "m\u00e4ki": 1, "yksinkertaista": 1, "samantyyppinen": 1, "opiskelijaryhm\u00e4": 1, "esitt\u00e4\u00e4": 8, "kurssille": 4, "asiasta": 1, "sellaisille": 1, "yliopisto-opintojen": 3, "mallin": 1, "suullista": 1, "formaalisti": 1, "nelj\u00e4nness\u00e4": 2, "k\u00e4ytett\u00e4viss\u00e4": 1, "termin": 1, "avaavat": 1, "joukkoja": 7, "riippumatta": 2, "ilmat": 1, "opetukseen": 1, "yht\u00e4suuri": 1, "viikolla": 1, "maailmojen": 1, "huomauttaa": 5, "taitamattomaksi": 1, "las-kuharjoitusten": 1, "mahdollisesti": 6, "pyritty": 2, "harva": 1, "subject": 1, "opettajilta": 1, "kielell\u00e4": 9, "lienee": 1, "t\u00e4m\u00e4ntyyppisi\u00e4": 1, "council": 1, "ainedidaktinen": 1, "tietojenk\u00e4sittelytieteen": 3, "lomakekyselyyn": 1, "s\u00e4hk\u00f6isesti": 1, "korrelaatiota": 1, "selke\u00e4n": 2, "hy\u00f6dyllisen\u00e4": 2, "en": 3, "listasivat": 1, "karkeasti": 1, "huomiota": 9, "taitava": 3, "edestakaista": 1, "pohdittaessa": 1, "k\u00e4yt\u00e4nn\u00f6n": 2, "suhtautua": 1, "vaatima": 1, "ajattelu": 8, "symboleiksi": 1, "tuovan": 1, "ty\u00f6el\u00e4m\u00e4": 1, "m\u00e4\u00e4r\u00e4\u00e4m\u00e4tt\u00f6m\u00e4st\u00e4": 1, "lauseita": 6, "saattoivat": 1, "ker\u00e4tyss\u00e4": 1, "kielenk\u00e4ytt\u00f6\u00f6n": 1, "verran": 2, "h\u00e4mmennykseen": 1, "jotka": 21, "233\u2013235": 1, "opiskelijoiden": 31, "yleisempi\u00e4": 1, "niilo": 1, "laatimaa": 1, "testin": 1, "symbolikielinen": 2, "lis\u00e4pisteet": 1, "liikutaan": 1, "nelj\u00e4": 5, "vaikkapa": 2, "nimetty": 1, "kvantitatiivinen": 2, "829-845": 1, "kattaa": 1, "keskustelleensa": 1, "painottuivat": 1, "raassina": 1, "hahmottamaan": 2, "n\u00e4in": 4, "mittaamisesta": 1, "ajattelet": 1, "rekisteriss\u00e4": 2, "huomasin": 1, "toisensa": 2, "esiintynyt": 3, "osajoukko": 1, "\u201c\ud835\udc34": 1, "tiukasti": 2, "josta": 9, "n\u00e4kym\u00e4tt\u00f6miin": 1, "ottaa": 3, "mik\u00e4": 11, "selostaa": 1, "varaan": 1, "esiintyi": 3, "ymm\u00e4rrett\u00e4vien": 1, "yl\u00f6sen": 1, "mekaanista": 1, "kehitt\u00e4v\u00e4\u00e4": 1, "tutkinut": 1, "turunen": 1, "piirt\u00e4\u00e4": 1, "toisessa": 1, "ww": 1, "esimerkkiteht\u00e4v\u00e4": 1, "ongelmia": 15, "vaihtoehdon": 2, "keskim\u00e4\u00e4rin": 1, "yksitt\u00e4iset": 1, "jaotellut": 1, "sopii": 2, "tyypillisten": 1, "v\u00e4hentynyt": 1, "pitk\u00e4n": 3, "sanoihin": 2, "koetilaisuuden": 1, "olikin": 1, "tavoitematriisia": 1, "osaamiskokemus": 1, "merkitsevyytt\u00e4": 3, "mkk": 1, "osa": 20, "aukot": 3, "novice": 1, "puutteelliset": 1, "poikkeavalla": 1, "lukeneet": 1, "2000": 4, "sense": 1, "kertomus": 1, "koodinvaihtoteht\u00e4vi\u00e4": 1, "t\u00e4rkeytt\u00e4": 1, "kielt\u00e4": 14, "osoita": 2, "luonnollista": 7, "kouluasteesta": 1, "oppilaita": 2, "tuntua": 2, "konkreettisia": 1, "teknillisess\u00e4": 1, "joukkoihin": 3, "nykyisyytt\u00e4": 1, "yhdistyy": 2, "osioihin": 2, "sivu": 1, "3(1": 1, "introductory": 1, "science": 2, "tilastotieteen": 9, "p-arvo0001": 1, "kirjallinen": 8, "saattaisi": 1, "tutkimusten": 2, "palauttamien": 1, "double": 2, "standardimalli": 1, "sivuaineopiskelijoita": 4, "hyv\u00e4t": 1, "t\u00e4llainen": 1, "krussel": 2, "t\u00e4ydent\u00e4m\u00e4\u00e4n": 1, "proseptuaalis-symbolisessa": 1, "t\u00e4sm\u00e4lliset": 1, "tulkinta": 1, "nolla": 1, "samankaltaisista": 1, "luonnontieteiden": 1, "sivum\u00e4\u00e4r\u00e4": 1, "niikko": 1, "lyhyet": 1, "soveltamisessa": 1, "hankalampaa": 2, "ajat": 1, "kyselee": 1, "jakautuvat": 2, "motivaation": 1, "ihanteiden": 1, "edellyt\u00e4": 1, "menestymiseen": 4, "muuttaminen": 1, "tarkemmin": 5, "aineistossa": 1, "omalla": 1, "v\u00e4rikk\u00e4int\u00e4": 1, "selvitt\u00e4\u00e4": 3, "opiskeli": 1, "tulkitsivat": 1, "menestyksen": 1, "pisteit\u00e4": 13, "loikkaamaan": 1, "press": 1, "kokeneet": 2, "summana": 1, "kirjataan": 1, "osallistujista": 1, "kotisivu": 1, "saman": 1, "kuviokielt\u00e4": 1, "\u00e4idinkielt\u00e4ni": 1, "kertauskurssi": 1, "paremmin": 4, "voisi": 10, "booky": 1, "brown": 1, "onko": 4, "kurssilta": 2, "opiskelleet": 1, "tietoa": 4, "arvioinnin": 5, "heikoimmin": 1, "saattoi": 7, "oppilaan": 4, "2013": 15, "yliopistomatematiikan": 4, "korrelaation": 1, "virheellinen": 4, "virkkeit\u00e4": 5, "kysymyst\u00e4": 2, "n\u00e4m\u00e4": 6, "perehtyen": 1, "vasta": 3, "tuloksia": 3, "antoi": 2, "tutkittiin": 4, "yl\u00e4p\u00e4\u00e4h\u00e4n": 2, "pystyy": 2, "t\u00e4ydent\u00e4mist\u00e4": 1, "ratkaisemaan": 1, "vastausten": 7, "opintojeni": 1, "ratkaisijaa": 1, "induktiotodistamisen": 1, "kielent\u00e4misharjoitusten": 1, "johdattelee": 2, "symposiumi": 1, "huomioon": 1, "tiedon": 3, "huomioidaan": 1, "tekij\u00e4": 4, "ropo": 1, "eniten": 1, "kielellisi\u00e4": 1, "varattu": 1, "\u201clanguage": 1, "lukiolainenhan": 1, "takertunut": 1, "arvioijasta": 3, "esitetyn": 1, "yht\u00e4l\u00f6lle": 1, "haasteena": 1, "tekemisen": 1, "harjoitusteht\u00e4vist\u00e4": 2, "ymm\u00e4rt\u00e4nyt": 2, "minulle": 3, "tottuneet": 3, "kun": 18, "muutama": 4, "itsest\u00e4": 2, "lausekkeesta": 1, "symbolikieliset": 3, "haparoinnin": 1, "oikean": 2, "vastausprosentti": 1, "teht\u00e4v\u00e4tyypit": 1, "ensimm\u00e4isen\u00e4": 1, "harjoittelun": 1, "t\u00e4rke\u00e4mm\u00e4ksi": 1, "kari": 2, "yhteispisteet": 2, "tuote": 1, "sekoittumista": 1, "sis\u00e4ist\u00e4nyt": 1, "13\u201314": 1, "kurssi": 4, "15(3": 1, "parhaiten": 4, "pistem\u00e4\u00e4r\u00e4n": 1, "nimenomaan": 3, "sanaa": 1, "oppimistilanne": 1, "k\u00e4site": 4, "koulutusasteella": 1, "apunaan": 1, "olleiden": 1, "kolmena": 1, "soveltavissa": 1, "matiikan": 1, "asioiden": 2, "yhdist\u00e4\u00e4": 1, "the": 20, "samat": 1, "kiinnostuin": 2, "kirjallisen": 7, "kuvaavat": 6, "kysyttiin": 1, "ratkaisusta": 5, "ilmoittautuneista": 2, "k\u00e4yd\u00e4\u00e4n": 2, "merkityksist\u00e4": 1, "osaamista": 2, "hankala": 1, "assessing": 3, "sill\u00e4": 10, "noudattaa": 1, "tehty\u00e4": 2, "joku": 1, "tietoista": 1, "8\u201310": 1, "oppiaine": 1, "luentomateriaalissa": 1, "kurssi-menestykseen\\n\\ntutkimus": 1, "ratkaistessaan": 1, "kuninkaankartanonm\u00e4elt\u00e4": 1, "omalle": 1, "kulusta": 1, "vaihtoehtoisesti": 1, "johdokset": 1, "pisteytyksess\u00e4": 2, "kielille": 1, "politics": 1, "mathematician\u2019s": 1, "selitys": 2, "symboleja": 1, "haltuun": 1, "university": 5, "todistusajattelua": 1, "korjataan": 1, "kuvaaminen": 2, "oppilaiden": 3, "antoisaa": 1, "my\u00f6sk\u00e4\u00e4n": 3, "t\u00e4sm\u00e4llisesti": 2, "pohdiskelemista": 1, "yksisuuntaisen": 1, "oppipoikamallin": 1, "kertoimen": 1, "pistem\u00e4\u00e4riss\u00e4": 1, "paremmalle": 1, "toteutettu": 1, "lukiomatematiikan": 1, "kehitty\u00e4": 1, "huomaa": 3, "24\u201326": 1, "kielent\u00e4mist\u00e4": 10, "tehostettu": 1, "esitystraditioihin": 1, "toisistaan": 1, "t\u00e4ll\u00f6in": 8, "ep\u00e4muodollisesta": 1, "va": 1, "keskustelusta": 1, "mahdollisimman": 7, "voisin": 1, "parantaa": 6, "p\u00e4\u00e4ss\u00e4\u00e4n": 1, "kurssipisteit\u00e4": 1, "m\u00e4\u00e4riteltyn\u00e4": 1, "yliopistoopiskelijoihin": 1, "niill\u00e4": 2, "eleet": 1, "yleisin": 1, "jossain": 1, "vastata": 1, "matemaatikkojen": 1, "annetussa": 1, "httpwwwfsdutafimenetelmaopetus": 1, "ehdotuksia": 1, "suurelta": 2, "vaiheen": 1, "kaavat": 3, "tilanteissa": 2, "puolella": 1, "functioning": 1, "pistett\u00e4": 23, "jokseenkin": 3, "luonnon": 1, "avoimissa": 1, "tekisin": 1, "kokonaisuutena": 1, "suhtautuvat": 5, "kielent\u00e4misteht\u00e4vi\u00e4": 6, "matemaattisessa": 7, "kehittymiseen": 1, "2008": 4, "vastaustaan": 1, "ongelmanratkaisutaidon": 2, "tekee": 2, "k\u00e4ytt\u00f6\u00f6n": 11, "heid\u00e4n": 4, "kouluttaminen": 1, "london": 3, "useita": 1, "ker\u00e4tess\u00e4ni": 1, "yksitt\u00e4inen": 1, "opetustaan": 1, "mtl": 3, "ohjeistuksesta": 1, "johdatus": 6, "111\u2013122": 1, "ulkopuolisenkin": 1, "symposium": 1, "lomakkeessa": 1, "ammatissa": 1, "edimensio": 1, "saanut": 1, "kuvasta": 8, "eritt\u00e4in": 5, "omaa": 8, "kiinnitt\u00e4\u00e4": 4, "valinneiden": 2, "heikko": 1, "useilla": 1, "joukko": 11, "asteikon": 3, "argumentoinnin": 1, "piilomerkityksi\u00e4": 2, "tutkittavalle": 1, "tavallaan": 1, "etenemist\u00e4": 1, "k\u00e4ytt\u00f6kelpoisena": 1, "kemiaa": 1}